{ "compressionlevel":-1,
 "editorsettings":
    {
     "chunksize":
        {
         "height":32,
         "width":32
        },
     "export":
        {
         "format":"json"
        }
    },
 "height":31,
 "infinite":false,
 "layers":[
        {
         "data":[0, 0, 0, 0, 0, 0, 0, 0, 0, 0, 0, 0, 0, 0, 0, 0, 0, 0, 0, 0, 0, 0, 0, 0, 0, 0, 0, 0, 0, 0, 0, 0, 0, 0, 0, 0, 0, 0, 0, 0, 0, 0, 0, 0, 0, 0, 0, 0, 0, 0, 0, 0, 0, 0, 0, 0, 0, 0, 0, 0, 0, 0, 0, 0, 0, 0, 0, 0, 0, 0, 0, 0, 0, 0, 0, 0, 0, 0, 0, 0, 0, 0, 0, 0, 0, 0, 0, 0, 0, 0, 0, 0, 0, 0, 0, 0, 0, 0, 0, 0, 0, 0, 0, 0, 0, 0, 0, 0, 0, 0, 0, 0, 0, 0, 0, 0, 0, 0, 0, 0, 0, 0, 0, 0, 0, 0, 0, 0, 0, 0, 0, 0, 0, 0, 0, 0, 0, 0, 0, 0, 0, 0, 0, 0, 0, 0, 0, 0, 0, 0, 0, 0, 0, 0, 0, 0, 0, 0, 0, 0, 0, 0, 0, 0, 0, 0, 0, 0, 0, 0, 0, 0, 0, 0, 0, 0, 0, 0, 0, 0, 0, 0, 0, 0, 0, 0, 0, 0, 0, 0, 0, 0, 0, 0, 0, 0, 0, 0, 0, 0, 0, 0, 0, 0, 0, 0, 0, 0, 0, 0, 0, 0, 0, 0, 0, 0, 0, 0, 0, 0, 0, 0, 0, 0, 0, 0, 0, 0, 0, 0, 0, 0, 0, 0, 0, 0, 0, 0, 0, 0, 0, 0, 0, 0, 0, 0, 0, 0, 0, 0, 0, 0, 0, 0, 0, 0, 0, 0, 0, 0, 0, 0, 0, 0, 0, 0, 0, 0, 0, 0, 0, 0, 0, 0, 0, 0, 0, 0, 0, 0, 0, 0, 0, 0, 0, 0, 0, 0, 0, 0, 0, 0, 0, 0, 0, 0, 0, 0, 0, 0, 0, 0, 0, 0, 0, 0, 0, 0, 0, 0, 0, 0, 0, 0, 0, 0, 0, 0, 0, 0, 0, 0, 0, 0, 0, 0, 0, 0, 0, 0, 0, 0, 0, 0, 0, 0, 0, 0, 0, 0, 0, 0, 0, 0, 0, 0, 0, 0, 0, 0, 0, 0, 0, 0, 0, 0, 0, 0, 0, 0, 0, 0, 0, 0, 0, 0, 0, 0, 0, 0, 0, 0, 0, 0, 0, 0, 0, 0, 0, 0, 0, 0, 0, 0, 0, 0, 0, 0, 0, 0, 0, 0, 0, 0, 0, 0, 0, 0, 0, 0, 0, 0, 0, 0, 0, 0, 0, 0, 0, 0, 0, 0, 0, 0, 0, 0, 0, 0, 0, 0, 0, 0, 0, 0, 0, 0, 0, 0, 0, 0, 0, 0, 0, 0, 0, 0, 0, 0, 0, 0, 0, 0, 0, 0, 0, 0, 0, 0, 0, 0, 0, 0, 0, 0, 0, 0, 0, 0, 0, 0, 0, 0, 0, 0, 0, 0, 0, 0, 0, 0, 0, 0, 0, 0, 0, 0, 0, 0, 0, 0, 0, 0, 0, 0, 0, 0, 0, 0, 0, 0, 0, 0, 0, 0, 0, 0, 0, 0, 0, 0, 0, 0, 0, 0, 0, 0, 0, 0, 0, 0, 0, 0, 0, 0, 0, 0, 0, 0, 0, 0, 0, 0, 0, 0, 0, 0, 0, 0, 0, 0, 0, 0, 0, 0, 0, 0, 0, 0, 0, 0, 0, 0, 0, 0, 0, 0, 0, 0, 0, 0, 0, 0, 0, 0, 0, 0, 0, 0, 0, 0, 0, 0, 0, 0, 0, 0, 0, 0, 0, 0, 0, 0, 0, 0, 0, 0, 0, 0, 0, 0, 0, 0, 0, 0, 0, 0, 0, 0, 0, 0, 0, 0, 0, 0, 0, 0, 0, 0, 0, 0, 0, 0, 0, 0, 0, 0, 0, 0, 0, 0, 0, 0, 0, 0, 0, 0, 0, 0, 0, 0, 0, 0, 0, 0, 0, 0, 0, 0, 0, 0, 0, 0, 0, 0, 0, 0, 0, 0, 0, 0, 0, 0, 0, 0, 0, 0, 0, 0, 0, 0, 0, 0, 0, 0, 0, 0, 0, 0, 0, 0, 0, 0, 0, 0, 0, 0, 0, 0, 0, 0, 0, 0, 0, 0, 0, 0, 0, 0, 0, 21153, 21153, 21153, 21153, 21153, 21153, 21153, 21153, 21153, 21153, 0, 0, 0, 0, 0, 0, 0, 0, 0, 0, 0, 0, 0, 0, 0, 21153, 21153, 21153, 21153, 21153, 21153, 21153, 21153, 0, 0, 0, 0, 0, 0, 0, 0, 0, 0, 0, 0, 0, 0, 0, 0, 0, 0, 0, 0, 0, 0, 0, 0, 0, 0, 0, 0, 0, 0, 0, 0],
         "height":31,
         "id":11,
         "name":"start",
         "opacity":1,
         "type":"tilelayer",
         "visible":true,
         "width":24,
         "x":0,
         "y":0
        }, 
        {
         "data":[21152, 21152, 21152, 21152, 21152, 21152, 21152, 21152, 21152, 21152, 21152, 21152, 21152, 21152, 21152, 21152, 21152, 21152, 21152, 21152, 21152, 21152, 21152, 21152, 21152, 21152, 21152, 21152, 21152, 21152, 21152, 21152, 21152, 21152, 21152, 21152, 21152, 21152, 21152, 21152, 21152, 21152, 21152, 21152, 21152, 21152, 21152, 21152, 21152, 21152, 0, 0, 0, 0, 0, 0, 0, 0, 0, 0, 0, 0, 0, 0, 0, 0, 0, 0, 0, 0, 21152, 21152, 0, 0, 0, 0, 0, 0, 0, 0, 0, 0, 21152, 21152, 21152, 21152, 0, 0, 0, 0, 0, 0, 0, 0, 0, 0, 0, 0, 0, 0, 0, 0, 0, 0, 0, 0, 0, 0, 0, 0, 0, 0, 0, 0, 0, 0, 0, 0, 0, 0, 0, 0, 0, 0, 0, 0, 0, 0, 0, 0, 0, 0, 0, 0, 0, 0, 0, 0, 0, 0, 0, 0, 0, 0, 0, 0, 0, 0, 0, 0, 0, 0, 0, 0, 0, 0, 0, 0, 0, 0, 0, 0, 0, 0, 0, 0, 0, 0, 0, 0, 0, 0, 0, 0, 0, 0, 0, 0, 0, 0, 0, 0, 0, 0, 0, 0, 0, 0, 0, 0, 0, 0, 0, 0, 0, 0, 0, 0, 0, 0, 0, 0, 0, 0, 0, 0, 0, 0, 0, 0, 0, 0, 0, 0, 0, 0, 0, 0, 0, 0, 0, 0, 0, 0, 0, 0, 0, 0, 0, 0, 0, 0, 0, 0, 0, 0, 0, 0, 0, 0, 0, 0, 0, 0, 0, 0, 0, 0, 0, 0, 0, 0, 0, 0, 0, 0, 0, 0, 0, 0, 0, 0, 0, 0, 0, 0, 0, 0, 0, 0, 0, 0, 0, 0, 0, 0, 0, 0, 0, 0, 0, 0, 0, 0, 0, 0, 0, 0, 0, 0, 0, 0, 0, 0, 0, 0, 0, 0, 0, 0, 0, 0, 0, 0, 0, 0, 0, 0, 0, 0, 0, 0, 0, 0, 0, 0, 0, 0, 0, 0, 0, 0, 0, 0, 0, 0, 0, 0, 0, 0, 0, 0, 0, 0, 0, 0, 0, 0, 0, 0, 0, 0, 0, 0, 0, 0, 0, 0, 0, 0, 0, 0, 0, 0, 0, 0, 0, 0, 0, 0, 0, 0, 0, 0, 0, 0, 0, 0, 0, 0, 0, 0, 0, 0, 0, 0, 0, 0, 0, 0, 0, 0, 0, 0, 0, 0, 0, 0, 0, 0, 0, 0, 0, 0, 0, 0, 0, 0, 0, 0, 0, 0, 0, 0, 0, 0, 0, 0, 0, 0, 0, 0, 0, 0, 0, 0, 0, 0, 0, 0, 0, 0, 0, 0, 0, 0, 0, 0, 0, 0, 0, 0, 0, 0, 0, 0, 0, 0, 0, 0, 0, 0, 0, 0, 0, 0, 0, 0, 0, 0, 0, 0, 0, 0, 0, 0, 0, 0, 0, 0, 0, 0, 0, 0, 0, 0, 0, 0, 0, 0, 0, 0, 0, 0, 0, 0, 0, 0, 0, 0, 0, 0, 0, 0, 0, 0, 0, 0, 0, 0, 0, 0, 0, 0, 0, 0, 0, 0, 0, 0, 0, 0, 0, 0, 0, 0, 0, 0, 0, 0, 0, 0, 0, 0, 0, 0, 0, 0, 0, 0, 0, 0, 0, 0, 0, 0, 0, 0, 0, 0, 0, 0, 0, 0, 0, 0, 0, 0, 0, 0, 0, 0, 0, 0, 0, 0, 0, 0, 0, 0, 0, 0, 0, 0, 0, 0, 0, 0, 0, 0, 0, 0, 0, 0, 0, 0, 0, 0, 0, 0, 0, 0, 0, 0, 0, 0, 0, 0, 0, 0, 0, 0, 0, 0, 0, 0, 0, 0, 0, 0, 0, 0, 0, 0, 0, 0, 0, 0, 0, 0, 0, 0, 0, 0, 0, 0, 0, 0, 0, 0, 0, 0, 0, 0, 0, 0, 0, 0, 0, 0, 0, 0, 0, 0, 0, 0, 0, 0, 0, 0, 0, 0, 0, 0, 0, 0, 0, 0, 0, 0, 0, 0, 0, 0, 0, 0, 0, 0, 0, 0, 0, 0, 0, 0, 0, 0, 0, 0, 0, 0, 0, 0, 0, 0, 0, 0, 0, 0, 0, 0, 0, 0, 0, 0, 0, 0, 0, 0, 0, 0, 0, 0, 0, 0, 0, 0, 0, 0, 0, 0, 0, 0, 0, 0, 0, 0, 21152, 21152, 21152, 21152, 21152, 21152, 21152, 21152, 0, 0, 0, 0, 0, 0, 0, 0, 21152, 21152, 21152, 21152, 21152, 21152, 21152, 21152, 21152, 21152, 21152, 21152, 21152, 21152, 21152, 21152, 0, 0, 0, 0, 0, 0, 0, 0, 21152, 21152, 21152, 21152, 21152, 21152, 21152, 21152],
         "height":31,
         "id":41,
         "name":"collides",
         "opacity":1,
         "type":"tilelayer",
         "visible":true,
         "width":24,
         "x":0,
         "y":0
        }, 
        {
         "data":[0, 0, 0, 0, 0, 0, 0, 0, 0, 0, 0, 0, 0, 0, 0, 0, 0, 0, 0, 0, 0, 0, 0, 0, 0, 0, 0, 0, 0, 0, 0, 0, 0, 0, 0, 0, 0, 0, 0, 0, 0, 0, 0, 0, 0, 0, 0, 0, 0, 0, 0, 0, 0, 0, 0, 0, 0, 0, 0, 0, 0, 0, 0, 0, 0, 0, 0, 0, 0, 0, 0, 0, 0, 0, 0, 0, 0, 0, 0, 0, 0, 0, 0, 0, 0, 0, 0, 0, 0, 0, 0, 0, 0, 0, 0, 0, 0, 0, 0, 0, 0, 0, 0, 0, 0, 0, 0, 0, 0, 0, 0, 0, 0, 0, 0, 0, 0, 0, 0, 0, 0, 0, 0, 0, 0, 0, 0, 0, 0, 0, 0, 0, 0, 0, 0, 0, 0, 0, 0, 0, 0, 0, 0, 0, 0, 0, 0, 0, 0, 0, 0, 0, 0, 0, 0, 0, 0, 0, 0, 0, 0, 0, 0, 0, 0, 0, 0, 0, 0, 0, 0, 0, 0, 0, 0, 0, 0, 0, 0, 0, 0, 0, 0, 0, 0, 0, 0, 0, 0, 0, 0, 0, 0, 0, 0, 0, 0, 0, 0, 0, 0, 0, 0, 0, 0, 0, 0, 0, 0, 0, 0, 0, 0, 0, 0, 0, 0, 0, 0, 0, 0, 0, 0, 0, 0, 0, 0, 0, 0, 0, 0, 0, 0, 0, 0, 0, 0, 0, 0, 0, 0, 0, 0, 0, 0, 0, 0, 0, 0, 0, 0, 0, 0, 0, 0, 0, 0, 0, 0, 0, 0, 0, 0, 0, 0, 0, 0, 0, 0, 0, 0, 0, 0, 0, 0, 0, 0, 0, 0, 0, 0, 0, 0, 0, 0, 0, 0, 0, 0, 0, 0, 0, 0, 0, 0, 0, 0, 0, 0, 0, 0, 0, 0, 0, 0, 0, 0, 0, 0, 0, 0, 0, 0, 0, 0, 0, 0, 0, 0, 0, 0, 0, 0, 0, 0, 0, 0, 0, 0, 0, 0, 0, 0, 0, 0, 0, 0, 0, 0, 0, 0, 0, 0, 0, 0, 0, 0, 0, 0, 0, 0, 0, 0, 0, 0, 0, 0, 0, 0, 0, 0, 0, 0, 0, 0, 0, 0, 0, 0, 0, 0, 0, 0, 0, 0, 0, 0, 0, 0, 0, 0, 0, 0, 0, 0, 0, 0, 0, 0, 0, 0, 0, 0, 0, 0, 0, 0, 0, 0, 0, 0, 0, 0, 0, 0, 0, 0, 0, 0, 0, 0, 0, 0, 0, 0, 0, 0, 0, 0, 0, 0, 0, 0, 0, 0, 0, 0, 0, 0, 0, 0, 0, 0, 0, 0, 0, 0, 0, 0, 0, 0, 0, 0, 0, 0, 0, 0, 0, 0, 0, 0, 0, 0, 0, 0, 0, 0, 0, 0, 0, 0, 0, 0, 0, 0, 0, 0, 0, 0, 0, 0, 0, 0, 0, 0, 0, 0, 0, 0, 0, 0, 0, 0, 0, 0, 0, 0, 0, 0, 0, 0, 0, 0, 0, 0, 0, 0, 0, 0, 0, 0, 0, 0, 0, 0, 0, 0, 0, 0, 0, 0, 0, 0, 0, 0, 0, 0, 0, 0, 0, 0, 0, 0, 0, 0, 0, 0, 0, 0, 0, 0, 0, 0, 0, 0, 0, 0, 0, 0, 0, 0, 0, 0, 0, 0, 0, 0, 0, 0, 0, 0, 0, 0, 0, 0, 0, 0, 0, 0, 0, 0, 0, 0, 0, 0, 0, 0, 0, 0, 0, 0, 0, 0, 0, 0, 0, 0, 0, 0, 0, 0, 0, 0, 0, 0, 0, 0, 0, 0, 0, 0, 0, 0, 0, 0, 0, 0, 0, 0, 0, 0, 0, 0, 0, 0, 0, 0, 0, 0, 0, 0, 0, 0, 0, 0, 0, 0, 0, 0, 0, 0, 0, 0, 0, 0, 0, 0, 0, 0, 0, 0, 0, 0, 0, 0, 0, 0, 0, 0, 0, 0, 0, 0, 0, 0, 0, 0, 0, 0, 0, 0, 0, 0, 0, 0, 0, 0, 0, 0, 0, 0, 0, 0, 0, 0, 0, 0, 0, 0, 0, 0, 0, 0, 0, 0, 0, 0, 0, 0, 0, 0, 0, 0, 0, 0, 0, 0, 0, 0, 0, 0, 0, 0, 0, 0, 0, 0, 0, 0, 0, 0, 0, 0, 0, 0, 0, 0, 0, 0, 0, 0, 0, 0, 0, 0, 0, 0, 0, 0, 0, 0, 0, 0, 0, 0, 0, 0, 0, 21159, 21159, 21159, 21159, 21159, 21159, 21159, 21159, 0, 0, 0, 0, 0, 0, 0, 0],
         "height":31,
         "id":26,
         "name":"exit",
         "opacity":1,
         "properties":[
                {
                 "name":"exitUrl",
                 "type":"string",
                 "value":"map.json#startLayer-amphi"
                }],
         "type":"tilelayer",
         "visible":true,
         "width":24,
         "x":0,
         "y":0
        }, 
        {
         "data":[0, 0, 0, 0, 0, 0, 0, 0, 0, 0, 0, 0, 0, 0, 0, 0, 0, 0, 0, 0, 0, 0, 0, 0, 0, 0, 0, 0, 0, 0, 0, 0, 0, 0, 0, 0, 0, 0, 0, 0, 0, 0, 0, 0, 0, 0, 0, 0, 0, 0, 21160, 21160, 21160, 21160, 21160, 21160, 0, 0, 0, 0, 0, 0, 0, 0, 21160, 21160, 21160, 21160, 21160, 21160, 0, 0, 21160, 21160, 21160, 21160, 21160, 21160, 21160, 21160, 0, 0, 0, 0, 0, 0, 0, 0, 21160, 21160, 21160, 21160, 21160, 21160, 21160, 21160, 21160, 21160, 21160, 21160, 21160, 21160, 21160, 21160, 21160, 21160, 21160, 21160, 21160, 21160, 21160, 21160, 21160, 21160, 21160, 21160, 21160, 21160, 21160, 21160, 21160, 21160, 21160, 21160, 21160, 21160, 21160, 21160, 21160, 21160, 21160, 21160, 21160, 21160, 21160, 21160, 21160, 21160, 21160, 21160, 21160, 21160, 21160, 21160, 21160, 21160, 21160, 21160, 21160, 21160, 21160, 21160, 21160, 21160, 21160, 21160, 21160, 21160, 21160, 21160, 21160, 21160, 21160, 21160, 21160, 21160, 21160, 21160, 21160, 21160, 21160, 21160, 21160, 21160, 21160, 21160, 21160, 21160, 21160, 21160, 21160, 21160, 21160, 21160, 21160, 21160, 21160, 21160, 21160, 21160, 21160, 21160, 21160, 21160, 21160, 21160, 21160, 21160, 21160, 21160, 21160, 21160, 21160, 21160, 21160, 21160, 21160, 21160, 21160, 21160, 21160, 21160, 21160, 21160, 21160, 21160, 21160, 21160, 21160, 21160, 21160, 21160, 21160, 21160, 21160, 21160, 21160, 21160, 21160, 21160, 21160, 21160, 21160, 21160, 21160, 21160, 21160, 21160, 21160, 21160, 21160, 21160, 21160, 21160, 21160, 21160, 21160, 21160, 21160, 21160, 21160, 21160, 21160, 21160, 21160, 21160, 21160, 21160, 21160, 21160, 21160, 21160, 21160, 21160, 21160, 21160, 21160, 21160, 21160, 21160, 21160, 21160, 21160, 21160, 21160, 21160, 21160, 21160, 21160, 21160, 21160, 21160, 21160, 21160, 21160, 21160, 21160, 21160, 21160, 21160, 21160, 21160, 21160, 21160, 21160, 21160, 21160, 21160, 21160, 21160, 21160, 21160, 21160, 21160, 21160, 21160, 21160, 21160, 21160, 21160, 21160, 21160, 21160, 21160, 21160, 21160, 21160, 21160, 21160, 21160, 21160, 21160, 21160, 21160, 21160, 21160, 21160, 21160, 21160, 21160, 21160, 21160, 21160, 21160, 21160, 21160, 21160, 21160, 21160, 21160, 21160, 21160, 21160, 21160, 21160, 21160, 21160, 21160, 21160, 21160, 21160, 21160, 21160, 21160, 21160, 21160, 21160, 21160, 21160, 21160, 21160, 21160, 21160, 21160, 21160, 21160, 21160, 21160, 21160, 21160, 21160, 21160, 21160, 21160, 21160, 21160, 21160, 21160, 21160, 21160, 21160, 21160, 21160, 21160, 21160, 21160, 21160, 21160, 21160, 21160, 21160, 21160, 21160, 21160, 21160, 21160, 21160, 21160, 21160, 21160, 21160, 21160, 21160, 21160, 21160, 21160, 21160, 21160, 21160, 21160, 21160, 21160, 21160, 21160, 21160, 21160, 21160, 21160, 21160, 21160, 21160, 21160, 21160, 21160, 21160, 21160, 21160, 21160, 21160, 21160, 21160, 21160, 21160, 21160, 21160, 21160, 21160, 21160, 21160, 21160, 21160, 21160, 21160, 21160, 21160, 21160, 21160, 21160, 21160, 21160, 21160, 21160, 21160, 21160, 21160, 21160, 21160, 21160, 21160, 21160, 21160, 21160, 21160, 21160, 21160, 21160, 21160, 21160, 21160, 21160, 21160, 21160, 21160, 21160, 21160, 21160, 21160, 21160, 21160, 21160, 21160, 21160, 21160, 21160, 21160, 21160, 21160, 21160, 21160, 21160, 21160, 21160, 21160, 21160, 21160, 21160, 21160, 21160, 21160, 21160, 21160, 21160, 21160, 21160, 21160, 21160, 21160, 21160, 21160, 21160, 21160, 21160, 21160, 21160, 21160, 21160, 21160, 21160, 21160, 21160, 21160, 21160, 21160, 21160, 21160, 21160, 21160, 21160, 21160, 21160, 21160, 21160, 21160, 21160, 21160, 21160, 21160, 21160, 21160, 21160, 21160, 21160, 21160, 21160, 21160, 21160, 21160, 21160, 21160, 21160, 21160, 21160, 21160, 21160, 21160, 21160, 21160, 21160, 21160, 21160, 21160, 21160, 21160, 21160, 21160, 21160, 21160, 21160, 21160, 21160, 21160, 21160, 21160, 21160, 21160, 21160, 21160, 21160, 21160, 21160, 21160, 21160, 21160, 21160, 21160, 21160, 21160, 21160, 21160, 21160, 21160, 21160, 21160, 21160, 21160, 21160, 21160, 21160, 21160, 21160, 21160, 21160, 21160, 21160, 21160, 21160, 21160, 21160, 21160, 21160, 21160, 21160, 21160, 21160, 21160, 21160, 21160, 21160, 21160, 21160, 21160, 21160, 21160, 21160, 21160, 21160, 21160, 21160, 21160, 21160, 21160, 21160, 21160, 21160, 21160, 21160, 21160, 21160, 21160, 21160, 21160, 21160, 21160, 21160, 21160, 21160, 21160, 21160, 21160, 21160, 21160, 21160, 21160, 21160, 21160, 21160, 21160, 21160, 21160, 21160, 21160, 21160, 21160, 21160, 21160, 21160, 21160, 21160, 21160, 21160, 21160, 21160, 21160, 21160, 21160, 21160, 21160, 21160, 21160, 21160, 21160, 21160, 21160, 21160, 21160, 21160, 21160, 21160, 21160, 21160, 21160, 21160, 21160, 21160, 21160, 21160, 0, 0, 0, 0, 0, 0, 0, 0, 21160, 21160, 21160, 21160, 21160, 21160, 21160, 21160, 0, 0, 0, 0, 0, 0, 0, 0, 0, 0, 0, 0, 0, 0, 0, 0, 21160, 21160, 21160, 21160, 21160, 21160, 21160, 21160, 0, 0, 0, 0, 0, 0, 0, 0],
         "height":31,
         "id":44,
         "name":"openWebsite-YouTubeLive-keynote",
         "opacity":1,
         "properties":[
                {
                 "name":"openWebsite",
                 "type":"string",
                 "value":"https:\/\/workadventure.agilille.fr\/agilille\/video_integration\/index.html"
                }, 
                {
                 "name":"openWebsitePolicy",
                 "type":"string",
                 "value":"fullscreen; accelerometer; autoplay; clipboard-write; encrypted-media; gyroscope; picture-in-picture"
                }],
         "type":"tilelayer",
         "visible":true,
         "width":24,
         "x":0,
         "y":0
        }, 
        {
         "data":[21154, 21154, 21154, 21154, 21154, 21154, 21154, 21154, 21154, 21154, 21154, 21154, 21154, 21154, 21154, 21154, 21154, 21154, 21154, 21154, 21154, 21154, 21154, 21154, 21154, 21154, 21154, 21154, 21154, 21154, 21154, 21154, 21154, 21154, 21154, 21154, 21154, 21154, 21154, 21154, 21154, 21154, 21154, 21154, 21154, 21154, 21154, 21154, 21154, 21154, 21154, 21154, 21154, 21154, 21154, 21154, 21154, 21154, 21154, 21154, 21154, 21154, 21154, 21154, 21154, 21154, 21154, 21154, 21154, 21154, 21154, 21154, 21154, 21154, 21154, 21154, 21154, 21154, 21154, 21154, 21154, 21154, 21154, 21154, 21154, 21154, 21154, 21154, 21154, 21154, 21154, 21154, 21154, 21154, 21154, 21154, 21154, 21154, 21154, 21154, 21154, 21154, 21154, 21154, 21154, 21154, 21154, 21154, 21154, 21154, 21154, 21154, 21154, 21154, 21154, 21154, 21154, 21154, 21154, 21154, 21154, 21154, 21154, 21154, 21154, 21154, 21154, 21154, 21154, 21154, 21154, 21154, 21154, 21154, 21154, 21154, 21154, 21154, 21154, 21154, 21154, 21154, 21154, 21154, 21154, 21154, 21154, 21154, 21154, 21154, 21154, 21154, 21154, 21154, 21154, 21154, 21154, 21154, 21154, 21154, 21154, 21154, 21154, 21154, 21154, 21154, 21154, 21154, 21154, 21154, 21154, 21154, 21154, 21154, 21154, 21154, 21154, 21154, 21154, 21154, 21154, 21154, 21154, 21154, 21154, 21154, 21154, 21154, 21154, 21154, 21154, 21154, 21154, 21154, 21154, 21154, 21154, 21154, 21154, 21154, 21154, 21154, 21154, 21154, 21154, 21154, 21154, 21154, 21154, 21154, 21154, 21154, 21154, 21154, 21154, 21154, 21154, 21154, 21154, 21154, 21154, 21154, 21154, 21154, 21154, 21154, 21154, 21154, 21154, 21154, 21154, 21154, 21154, 21154, 21154, 21154, 21154, 21154, 21154, 21154, 21154, 21154, 21154, 21154, 21154, 21154, 21154, 21154, 21154, 21154, 21154, 21154, 21154, 21154, 21154, 21154, 21154, 21154, 21154, 21154, 21154, 21154, 21154, 21154, 21154, 21154, 21154, 21154, 21154, 21154, 21154, 21154, 21154, 21154, 21154, 21154, 21154, 21154, 21154, 21154, 21154, 21154, 21154, 21154, 21154, 21154, 21154, 21154, 21154, 21154, 21154, 21154, 21154, 21154, 21154, 21154, 21154, 21154, 21154, 21154, 21154, 21154, 21154, 21154, 21154, 21154, 21154, 21154, 21154, 21154, 21154, 21154, 21154, 21154, 21154, 21154, 21154, 21154, 21154, 21154, 21154, 21154, 21154, 21154, 21154, 21154, 21154, 21154, 21154, 21154, 21154, 21154, 21154, 21154, 21154, 21154, 21154, 21154, 21154, 21154, 21154, 21154, 21154, 21154, 21154, 21154, 21154, 21154, 21154, 21154, 21154, 21154, 21154, 21154, 21154, 21154, 21154, 21154, 21154, 21154, 21154, 21154, 21154, 21154, 21154, 21154, 21154, 21154, 21154, 21154, 21154, 21154, 21154, 21154, 21154, 21154, 21154, 21154, 21154, 21154, 21154, 21154, 21154, 21154, 21154, 21154, 21154, 21154, 21154, 21154, 21154, 21154, 21154, 21154, 21154, 21154, 21154, 21154, 21154, 21154, 21154, 21154, 21154, 21154, 21154, 21154, 21154, 21154, 21154, 21154, 21154, 21154, 21154, 21154, 21154, 21154, 21154, 21154, 21154, 21154, 21154, 21154, 21154, 21154, 21154, 21154, 21154, 21154, 21154, 21154, 21154, 21154, 21154, 21154, 21154, 21154, 21154, 21154, 21154, 21154, 21154, 21154, 21154, 21154, 21154, 21154, 21154, 21154, 21154, 21154, 21154, 21154, 21154, 21154, 21154, 21154, 21154, 21154, 21154, 21154, 21154, 21154, 21154, 21154, 21154, 21154, 21154, 21154, 21154, 21154, 21154, 21154, 21154, 21154, 21154, 21154, 21154, 21154, 21154, 21154, 21154, 21154, 21154, 21154, 21154, 21154, 21154, 21154, 21154, 21154, 21154, 21154, 21154, 21154, 21154, 21154, 21154, 21154, 21154, 21154, 21154, 21154, 21154, 21154, 21154, 21154, 21154, 21154, 21154, 21154, 21154, 21154, 21154, 21154, 21154, 21154, 21154, 21154, 21154, 21154, 21154, 21154, 21154, 21154, 21154, 21154, 21154, 21154, 21154, 21154, 21154, 21154, 21154, 21154, 21154, 21154, 21154, 21154, 21154, 21154, 21154, 21154, 21154, 21154, 21154, 21154, 21154, 21154, 21154, 21154, 21154, 21154, 21154, 21154, 21154, 21154, 21154, 21154, 21154, 21154, 21154, 21154, 21154, 21154, 21154, 21154, 21154, 21154, 21154, 21154, 21154, 21154, 21154, 21154, 21154, 21154, 21154, 21154, 21154, 21154, 21154, 21154, 21154, 21154, 21154, 21154, 21154, 21154, 21154, 21154, 21154, 21154, 21154, 21154, 21154, 21154, 21154, 21154, 21154, 21154, 21154, 21154, 21154, 21154, 21154, 21154, 21154, 21154, 21154, 21154, 21154, 21154, 21154, 21154, 21154, 21154, 21154, 21154, 21154, 21154, 21154, 21154, 21154, 21154, 21154, 21154, 21154, 21154, 21154, 21154, 21154, 21154, 21154, 21154, 21154, 21154, 21154, 21154, 21154, 21154, 21154, 21154, 21154, 21154, 21154, 21154, 21154, 21154, 21154, 21154, 21154, 21154, 21154, 21154, 21154, 21154, 21154, 21154, 21154, 21154, 21154, 21154, 21154, 21154, 21154, 21154, 21154, 21154, 21154, 21154, 21154, 21154, 21154, 21154, 21154, 21154, 21154, 21154, 21154, 21154, 21154, 21154, 21154, 21154, 21154, 21154, 21154, 21154, 21154, 21154, 21154, 21154, 21154, 21154, 21154, 21154, 21154, 21154, 21154, 21154, 21154, 21154, 21154, 21154, 21154, 21154, 21154, 21154, 21154, 21154, 21154, 21154, 21154, 21154, 21154, 21154, 21154, 21154, 21154, 21154, 21154, 21154, 21154, 21154, 21154, 21154, 21154, 21154, 21154, 21154, 21154, 21154, 21154, 21154, 21154, 21154, 21154, 21154, 21154, 21154, 21154, 21154, 21154, 21154],
         "height":31,
         "id":46,
         "name":"silent",
         "opacity":1,
         "properties":[
                {
                 "name":"silent",
                 "type":"bool",
                 "value":true
                }],
         "type":"tilelayer",
         "visible":true,
         "width":24,
         "x":0,
         "y":0
        }, 
        {
         "data":[0, 0, 0, 0, 0, 0, 0, 0, 0, 0, 0, 0, 0, 0, 0, 0, 0, 0, 0, 0, 0, 0, 0, 0, 0, 0, 0, 0, 0, 0, 0, 0, 0, 0, 0, 0, 0, 0, 0, 0, 0, 0, 0, 0, 0, 0, 0, 0, 15910, 15910, 15910, 15910, 15910, 15910, 15910, 15910, 15910, 15910, 15910, 15910, 15910, 15910, 15910, 15910, 15910, 15910, 15910, 15910, 15910, 15910, 15910, 15910, 15910, 15910, 15910, 15910, 15910, 15910, 15910, 15910, 15910, 15910, 15910, 15910, 15910, 15910, 15910, 15910, 15910, 15910, 15910, 15910, 15910, 15910, 15910, 15910, 15910, 15910, 15910, 15910, 15910, 15910, 15910, 15910, 15910, 15910, 15910, 15910, 15910, 15910, 15910, 15910, 15910, 15910, 15910, 15910, 15910, 15910, 15910, 15910, 15910, 15910, 15910, 15910, 15910, 15910, 15910, 15910, 15910, 15910, 15910, 15910, 15910, 15910, 15910, 15910, 15910, 15910, 15910, 15910, 15910, 15910, 15910, 15910, 15910, 15910, 15910, 15910, 15910, 15910, 15910, 15910, 15910, 15910, 15910, 15910, 15910, 15910, 15910, 15910, 15910, 15910, 15910, 15910, 15910, 15910, 15910, 15910, 15910, 15910, 15910, 15910, 15910, 15910, 15910, 15910, 15910, 15910, 15910, 15910, 15910, 15910, 15910, 15910, 15910, 15910, 15910, 15910, 15910, 15910, 15910, 15910, 15910, 15910, 15910, 15910, 15910, 15910, 15910, 15910, 15910, 15910, 15910, 15910, 15910, 15910, 15910, 15910, 15910, 15910, 15910, 15910, 15910, 15910, 15910, 15910, 15910, 15910, 15910, 15910, 15910, 15910, 15910, 15910, 15910, 15910, 15910, 15910, 15910, 15910, 15910, 15910, 15910, 15910, 15910, 15910, 15910, 15910, 15910, 15910, 15910, 15910, 15910, 15910, 15910, 15910, 15910, 15910, 15910, 15910, 15910, 15910, 15910, 15910, 15910, 15910, 15910, 15910, 15910, 15910, 15910, 15910, 15910, 15910, 15910, 15910, 15910, 15910, 15910, 15910, 15910, 15910, 15910, 15910, 15910, 15910, 15910, 15910, 15910, 15910, 15910, 15910, 15910, 15910, 15910, 15910, 15910, 15910, 15910, 15910, 15910, 15910, 15910, 15910, 15910, 15910, 15910, 15910, 15910, 15910, 15910, 15910, 15910, 15910, 15910, 15910, 15910, 15910, 15910, 15910, 15910, 15910, 15910, 15910, 15910, 15910, 15910, 15910, 15910, 15910, 15910, 15910, 15910, 15910, 15910, 15910, 15910, 15910, 15910, 15910, 15910, 15910, 15910, 15910, 15910, 15910, 15910, 15910, 15910, 15910, 15910, 15910, 15910, 15910, 15910, 15910, 15910, 15910, 15910, 15910, 15910, 15910, 15910, 15910, 15910, 15910, 15910, 15910, 15910, 15910, 15910, 15910, 15910, 15910, 15910, 15910, 15910, 15910, 15910, 15910, 15910, 15910, 15910, 15910, 15910, 15910, 15910, 15910, 15910, 15910, 15910, 15910, 15910, 15910, 15910, 15910, 15910, 15910, 15910, 15910, 15910, 15910, 15910, 15910, 15910, 15910, 15910, 15910, 15910, 15910, 15910, 15910, 15910, 15910, 15910, 15910, 15910, 15910, 15910, 15910, 15910, 15910, 15910, 15910, 15910, 15910, 15910, 15910, 15910, 15910, 15910, 15910, 15910, 15910, 15910, 15910, 15910, 15910, 15910, 15910, 15910, 15910, 15910, 15910, 15910, 15910, 15910, 15910, 15910, 15910, 15910, 15910, 15910, 15910, 15910, 15910, 15910, 15910, 15910, 15910, 15910, 15910, 15910, 15910, 15910, 15910, 15910, 15910, 15910, 15910, 15910, 15910, 15910, 15910, 15910, 15910, 15910, 15910, 15910, 15910, 15910, 15910, 15910, 15910, 15910, 15910, 15910, 15910, 15910, 15910, 15910, 15910, 15910, 15910, 15910, 15910, 15910, 15910, 15910, 15910, 15910, 15910, 15910, 15910, 15910, 15910, 15910, 15910, 15910, 15910, 15910, 15910, 15910, 15910, 15910, 15910, 15910, 15910, 15910, 15910, 15910, 15910, 15910, 15910, 15910, 15910, 15910, 15910, 15910, 15910, 15910, 15910, 15910, 15910, 15910, 15910, 15910, 15910, 15910, 15910, 15910, 15910, 15910, 15910, 15910, 15910, 15910, 15910, 15910, 15910, 15910, 15910, 15910, 15910, 15910, 15910, 15910, 15910, 15910, 15910, 15910, 15910, 15910, 15910, 15910, 15910, 15910, 15910, 15910, 15910, 15910, 15910, 15910, 15910, 15910, 15910, 15910, 15910, 15910, 15910, 15910, 15910, 15910, 15910, 15910, 15910, 15910, 15910, 15910, 15910, 15910, 15910, 15910, 15910, 15910, 15910, 15910, 15910, 15910, 15910, 15910, 15910, 15910, 15910, 15910, 15910, 15910, 15910, 15910, 15910, 15910, 15910, 15910, 15910, 15910, 15910, 15910, 15910, 15910, 15910, 15910, 15910, 15910, 15910, 15910, 15910, 15910, 15910, 15910, 15910, 15910, 15910, 15910, 15910, 15910, 15910, 15910, 15910, 15910, 15910, 15910, 15910, 15910, 15910, 15910, 15910, 15910, 15910, 15910, 15910, 15910, 15910, 15910, 15910, 15910, 15910, 15910, 15910, 15910, 15910, 15910, 15910, 15910, 15910, 15910, 15910, 15910, 15910, 15910, 15910, 15910, 15910, 15910, 15910, 15910, 15910, 15910, 15910, 15910, 15910, 15910, 15910, 15910, 15910, 15910, 15910, 15910, 15910, 15910, 15910, 15910, 15910, 15910, 15910, 15910, 15910, 15910, 15910, 15910, 15910, 15910, 15910, 15910, 15910, 15910, 15910, 15910, 15910, 15910, 15910, 15910, 15910, 15910, 15910, 15910, 15910, 15910, 15910, 15910, 15910, 15910, 15910, 15910, 15910, 15910, 15910, 15910, 15910, 15910, 15910, 15910, 15910, 15910, 15910, 15910, 15910, 15910, 15910, 15910, 15910, 15910, 15910, 15910, 15910, 15910, 15910, 15910, 15910, 15910, 15910, 15910, 15910, 15910, 15910],
         "height":31,
         "id":42,
         "name":"floor",
         "opacity":1,
         "type":"tilelayer",
         "visible":true,
         "width":24,
         "x":0,
         "y":0
        }, 
        {
         "data":[0, 0, 0, 0, 0, 0, 0, 0, 0, 0, 0, 0, 0, 0, 0, 0, 0, 0, 0, 0, 0, 0, 0, 0, 0, 0, 0, 0, 0, 0, 0, 0, 0, 0, 0, 0, 0, 0, 0, 0, 0, 0, 0, 0, 0, 0, 0, 0, 0, 0, 0, 0, 8116, 8117, 8117, 8117, 8117, 8117, 8117, 8117, 8117, 8117, 8117, 8117, 8117, 8117, 8117, 8118, 0, 0, 0, 0, 0, 0, 0, 0, 8135, 8136, 8136, 8136, 8136, 8136, 8136, 8136, 8136, 8136, 8136, 8136, 8136, 8136, 8136, 8137, 0, 0, 0, 0, 0, 0, 0, 0, 8135, 8136, 8136, 8136, 8136, 8136, 8136, 8136, 8136, 8136, 8136, 8136, 8136, 8136, 8136, 8137, 0, 0, 0, 0, 0, 0, 0, 0, 8135, 8136, 8136, 8136, 8136, 8136, 8136, 8136, 8136, 8136, 8136, 8136, 8136, 8136, 8136, 8137, 0, 0, 0, 0, 0, 0, 0, 0, 8135, 8136, 8136, 8136, 8136, 8136, 8136, 8136, 8136, 8136, 8136, 8136, 8136, 8136, 8136, 8137, 0, 0, 0, 0, 0, 0, 0, 0, 8135, 8136, 8136, 8136, 8136, 8136, 8136, 8136, 8136, 8136, 8136, 8136, 8136, 8136, 8136, 8137, 0, 0, 0, 0, 0, 0, 0, 0, 8135, 8136, 8136, 8136, 8136, 8136, 8136, 8136, 8136, 8136, 8136, 8136, 8136, 8136, 8136, 8137, 0, 0, 0, 0, 0, 0, 0, 0, 8135, 8136, 8136, 8136, 8136, 8136, 8136, 8136, 8136, 8136, 8136, 8136, 8136, 8136, 8136, 8137, 0, 0, 0, 0, 0, 0, 0, 0, 8135, 8136, 8136, 8136, 8136, 8136, 8136, 8136, 8136, 8136, 8136, 8136, 8136, 8136, 8136, 8137, 0, 0, 0, 0, 0, 0, 0, 0, 8135, 8136, 8136, 8136, 8136, 8136, 8136, 8136, 8136, 8136, 8136, 8136, 8136, 8136, 8136, 8137, 0, 0, 0, 0, 0, 0, 0, 0, 8135, 8136, 8136, 8136, 8136, 8136, 8136, 8136, 8136, 8136, 8136, 8136, 8136, 8136, 8136, 8137, 0, 0, 0, 0, 0, 0, 0, 0, 8135, 8136, 8136, 8136, 8136, 8136, 8136, 8136, 8136, 8136, 8136, 8136, 8136, 8136, 8136, 8137, 0, 0, 0, 0, 0, 0, 0, 0, 8135, 8136, 8136, 8136, 8136, 8136, 8136, 8136, 8136, 8136, 8136, 8136, 8136, 8136, 8136, 8137, 0, 0, 0, 0, 0, 0, 0, 0, 8135, 8136, 8136, 8136, 8136, 8136, 8136, 8136, 8136, 8136, 8136, 8136, 8136, 8136, 8136, 8137, 0, 0, 0, 0, 0, 0, 0, 0, 8135, 8136, 8136, 8136, 8136, 8136, 8136, 8136, 8136, 8136, 8136, 8136, 8136, 8136, 8136, 8137, 0, 0, 0, 0, 0, 0, 0, 0, 8135, 8136, 8136, 8136, 8136, 8136, 8136, 8136, 8136, 8136, 8136, 8136, 8136, 8136, 8136, 8137, 0, 0, 0, 0, 0, 0, 0, 0, 8135, 8136, 8136, 8136, 8136, 8136, 8136, 8136, 8136, 8136, 8136, 8136, 8136, 8136, 8136, 8137, 0, 0, 0, 0, 0, 0, 0, 0, 8135, 8136, 8136, 8136, 8136, 8136, 8136, 8136, 8136, 8136, 8136, 8136, 8136, 8136, 8136, 8137, 0, 0, 0, 0, 0, 0, 0, 0, 8135, 8136, 8136, 8136, 8136, 8136, 8136, 8136, 8136, 8136, 8136, 8136, 8136, 8136, 8136, 8137, 0, 0, 0, 0, 0, 0, 0, 0, 8135, 8136, 8136, 8136, 8136, 8136, 8136, 8136, 8136, 8136, 8136, 8136, 8136, 8136, 8136, 8137, 0, 0, 0, 0, 0, 0, 0, 0, 8135, 8136, 8136, 8136, 8136, 8136, 8136, 8136, 8136, 8136, 8136, 8136, 8136, 8136, 8136, 8137, 0, 0, 0, 0, 0, 0, 0, 0, 8135, 8136, 8136, 8136, 8136, 8136, 8136, 8136, 8136, 8136, 8136, 8136, 8136, 8136, 8136, 8137, 0, 0, 0, 0, 0, 0, 0, 0, 8135, 8136, 8136, 8136, 8136, 8136, 8136, 8136, 8136, 8136, 8136, 8136, 8136, 8136, 8136, 8137, 0, 0, 0, 0, 0, 0, 0, 0, 8135, 8136, 8136, 8136, 8136, 8136, 8136, 8136, 8136, 8136, 8136, 8136, 8136, 8136, 8136, 8137, 0, 0, 0, 0, 0, 0, 0, 0, 8135, 8136, 8136, 8136, 8136, 8136, 8136, 8136, 8136, 8136, 8136, 8136, 8136, 8136, 8136, 8137, 0, 0, 0, 0, 0, 0, 0, 0, 8154, 8155, 8155, 8155, 8155, 8155, 8155, 8155, 8155, 8155, 8155, 8155, 8155, 8155, 8155, 8159, 0, 0, 0, 0, 0, 0, 0, 0, 0, 0, 0, 0, 0, 0, 0, 0, 0, 0, 0, 0, 0, 0, 0, 0, 0, 0, 0, 0, 0, 0, 0, 0, 0, 0, 0, 0, 21033, 21035, 21033, 21035, 21033, 21035, 21033, 21035, 0, 0, 0, 0, 0, 0, 0, 0, 0, 0, 0, 0, 0, 0, 0, 0, 21033, 21035, 21033, 21035, 21033, 21035, 21033, 21035, 0, 0, 0, 0, 0, 0, 0, 0],
         "height":31,
         "id":2,
         "name":"bottom",
         "opacity":1,
         "properties":[
                {
                 "name":"silent",
                 "type":"bool",
                 "value":true
                }],
         "type":"tilelayer",
         "visible":true,
         "width":24,
         "x":0,
         "y":0
        }, 
        {
         "data":[19892, 19892, 19892, 19892, 19892, 19892, 19892, 19892, 19892, 19892, 19892, 19892, 19892, 19892, 19892, 19892, 19892, 19892, 19892, 19892, 19892, 19892, 19892, 19892, 19892, 19892, 19892, 19892, 19892, 19892, 19892, 19892, 19892, 19892, 19892, 19892, 19892, 19892, 19892, 19892, 19892, 19892, 19892, 19892, 19892, 19892, 19892, 19892, 0, 0, 8116, 8117, 8117, 8117, 8117, 0, 0, 0, 0, 0, 0, 0, 0, 0, 0, 0, 0, 8117, 8117, 8118, 0, 0, 0, 0, 8135, 8136, 8136, 0, 0, 0, 0, 0, 0, 0, 0, 0, 0, 0, 0, 0, 0, 8136, 8136, 8137, 0, 0, 0, 0, 8135, 8136, 8136, 0, 0, 0, 0, 0, 0, 0, 0, 0, 0, 0, 0, 0, 0, 8136, 8136, 8137, 0, 0, 0, 0, 8135, 8136, 8136, 0, 0, 0, 0, 0, 0, 0, 0, 0, 0, 0, 0, 0, 0, 8136, 8136, 8137, 0, 0, 0, 0, 8135, 8136, 8136, 0, 0, 0, 0, 0, 0, 0, 0, 0, 0, 0, 0, 0, 0, 8136, 8136, 8137, 0, 0, 0, 0, 8135, 8136, 8136, 0, 0, 0, 0, 0, 0, 0, 0, 0, 0, 0, 0, 0, 0, 8136, 8136, 8137, 0, 0, 0, 0, 8135, 8136, 8136, 0, 0, 0, 0, 0, 0, 0, 0, 0, 0, 0, 0, 0, 0, 8136, 8136, 8137, 0, 0, 0, 0, 8135, 8136, 8136, 0, 0, 0, 0, 0, 0, 0, 0, 0, 0, 0, 0, 0, 0, 8136, 8136, 8137, 0, 0, 0, 0, 8135, 8136, 8136, 0, 0, 0, 0, 0, 0, 0, 0, 0, 0, 0, 0, 0, 0, 8136, 8136, 8137, 0, 0, 0, 0, 8135, 8136, 8136, 0, 0, 0, 0, 0, 0, 0, 0, 0, 0, 0, 0, 0, 0, 8136, 8136, 8137, 0, 0, 0, 0, 8135, 8136, 8136, 0, 0, 0, 0, 0, 0, 0, 0, 0, 0, 0, 0, 0, 0, 8136, 8136, 8137, 0, 0, 0, 0, 8135, 8136, 8136, 0, 0, 0, 0, 0, 0, 0, 0, 0, 0, 0, 0, 0, 0, 8136, 8136, 8137, 0, 0, 0, 0, 8135, 8136, 8136, 0, 0, 0, 0, 0, 0, 0, 0, 0, 0, 0, 0, 0, 0, 8136, 8136, 8137, 0, 0, 0, 0, 8135, 8136, 8136, 0, 0, 0, 0, 0, 0, 0, 0, 0, 0, 0, 0, 0, 0, 8136, 8136, 8137, 0, 0, 0, 0, 8135, 8136, 8136, 0, 0, 0, 0, 0, 0, 0, 0, 0, 0, 0, 0, 0, 0, 8136, 8136, 8137, 0, 0, 0, 0, 8135, 8136, 8136, 0, 0, 0, 0, 0, 0, 0, 0, 0, 0, 0, 0, 0, 0, 8136, 8136, 8137, 0, 0, 0, 0, 8135, 8136, 8136, 0, 0, 0, 0, 0, 0, 0, 0, 0, 0, 0, 0, 0, 0, 8136, 8136, 8137, 0, 0, 0, 0, 8135, 8136, 8136, 0, 0, 0, 0, 0, 0, 0, 0, 0, 0, 0, 0, 0, 0, 8136, 8136, 8137, 0, 0, 0, 0, 8135, 8136, 8136, 0, 0, 0, 0, 0, 0, 0, 0, 0, 0, 0, 0, 0, 0, 8136, 8136, 8137, 0, 0, 0, 0, 8135, 8136, 8136, 0, 0, 0, 0, 0, 0, 0, 0, 0, 0, 0, 0, 0, 0, 8136, 8136, 8137, 0, 0, 0, 0, 8135, 8136, 8136, 0, 0, 0, 0, 0, 0, 0, 0, 0, 0, 0, 0, 0, 0, 8136, 8136, 8137, 0, 0, 0, 0, 8135, 8136, 8136, 0, 0, 0, 0, 0, 0, 0, 0, 0, 0, 0, 0, 0, 0, 8136, 8136, 8137, 0, 0, 0, 0, 8135, 8136, 8136, 0, 0, 0, 0, 0, 0, 0, 0, 0, 0, 0, 0, 0, 0, 8136, 8136, 8137, 0, 0, 0, 0, 8135, 8136, 8136, 0, 0, 0, 0, 0, 0, 0, 0, 0, 0, 0, 0, 0, 0, 8136, 8136, 8137, 0, 0, 0, 0, 8135, 8136, 8136, 0, 0, 0, 0, 0, 0, 0, 0, 0, 0, 0, 0, 0, 0, 8136, 8136, 8137, 0, 0, 0, 0, 8154, 8155, 8155, 0, 0, 0, 0, 0, 0, 0, 0, 0, 0, 0, 0, 0, 0, 8155, 8155, 8156, 0, 0, 0, 0, 0, 0, 0, 0, 0, 0, 0, 0, 0, 0, 0, 0, 0, 0, 0, 0, 0, 0, 0, 0, 0, 0, 19892, 19892, 19892, 19892, 19892, 19892, 19892, 19892, 0, 0, 0, 0, 0, 0, 0, 0, 19892, 19892, 19892, 19892, 19892, 19892, 19892, 19892, 19892, 19892, 19892, 19892, 19892, 19892, 19892, 19892, 0, 0, 0, 0, 0, 0, 0, 0, 19892, 19892, 19892, 19892, 19892, 19892, 19892, 19892],
         "height":31,
         "id":40,
         "name":"wall",
         "opacity":1,
         "type":"tilelayer",
         "visible":true,
         "width":24,
         "x":0,
         "y":0
        }, 
        {
         "data":[6062, 6062, 6062, 6062, 6062, 6062, 6062, 6062, 6062, 6062, 6062, 6062, 6062, 6062, 6062, 6062, 6062, 6062, 6062, 6062, 6062, 6062, 6062, 6062, 0, 18657, 0, 18657, 0, 18658, 0, 18658, 0, 0, 0, 0, 0, 0, 0, 0, 18658, 0, 18658, 0, 18657, 0, 18657, 0, 0, 0, 0, 0, 0, 0, 0, 0, 0, 0, 0, 0, 0, 0, 0, 0, 0, 0, 0, 0, 0, 0, 0, 0, 0, 0, 0, 0, 0, 0, 0, 0, 0, 0, 0, 0, 0, 0, 0, 0, 0, 0, 0, 0, 0, 0, 0, 0, 0, 0, 0, 0, 0, 0, 0, 0, 0, 0, 0, 0, 0, 0, 0, 0, 0, 0, 0, 0, 0, 0, 0, 0, 0, 0, 0, 0, 0, 0, 0, 0, 0, 0, 0, 0, 0, 0, 0, 0, 0, 0, 0, 0, 0, 0, 0, 0, 0, 0, 0, 0, 0, 0, 0, 0, 0, 0, 0, 0, 0, 0, 0, 0, 0, 0, 0, 0, 0, 0, 0, 0, 0, 0, 0, 0, 0, 0, 0, 0, 0, 0, 0, 0, 0, 0, 0, 0, 0, 0, 0, 0, 0, 0, 0, 0, 0, 0, 0, 0, 0, 0, 0, 0, 0, 0, 0, 0, 0, 0, 0, 0, 0, 0, 0, 0, 0, 0, 0, 0, 0, 0, 0, 0, 0, 0, 0, 0, 0, 0, 0, 0, 0, 0, 0, 0, 0, 0, 0, 0, 0, 0, 0, 0, 0, 0, 0, 0, 0, 0, 0, 0, 0, 0, 0, 0, 0, 0, 0, 0, 0, 0, 0, 0, 0, 0, 0, 0, 0, 0, 0, 0, 0, 0, 0, 0, 0, 0, 0, 0, 0, 0, 0, 0, 0, 0, 0, 0, 0, 0, 0, 0, 0, 0, 0, 0, 0, 0, 0, 0, 0, 0, 0, 0, 0, 0, 0, 0, 0, 0, 0, 0, 0, 0, 0, 0, 0, 0, 0, 0, 0, 0, 0, 0, 0, 0, 0, 0, 0, 0, 0, 0, 0, 0, 0, 0, 0, 0, 0, 0, 0, 0, 0, 0, 0, 0, 0, 0, 0, 0, 0, 0, 0, 0, 0, 0, 0, 0, 0, 0, 0, 0, 0, 0, 0, 0, 0, 0, 0, 0, 0, 0, 0, 0, 0, 0, 0, 0, 0, 0, 0, 0, 0, 0, 0, 0, 0, 0, 0, 0, 0, 0, 0, 0, 0, 0, 0, 0, 0, 0, 0, 0, 0, 0, 0, 0, 0, 0, 0, 0, 0, 0, 0, 0, 0, 0, 0, 0, 0, 0, 0, 0, 0, 0, 0, 0, 0, 0, 0, 0, 0, 0, 0, 0, 0, 0, 0, 0, 0, 0, 0, 0, 0, 0, 0, 0, 0, 0, 0, 0, 0, 0, 0, 0, 0, 0, 0, 0, 0, 0, 0, 0, 0, 0, 0, 0, 0, 0, 0, 0, 0, 0, 0, 0, 0, 0, 0, 0, 0, 0, 0, 0, 0, 0, 0, 0, 0, 0, 0, 0, 0, 0, 0, 0, 0, 0, 0, 0, 0, 0, 0, 0, 0, 0, 0, 0, 0, 0, 0, 0, 0, 0, 0, 0, 0, 0, 0, 0, 0, 0, 0, 0, 0, 0, 0, 0, 0, 0, 0, 0, 0, 0, 0, 0, 0, 0, 0, 0, 0, 0, 0, 0, 0, 0, 0, 0, 0, 0, 0, 0, 0, 0, 0, 0, 0, 0, 0, 0, 0, 0, 0, 0, 0, 0, 0, 0, 0, 0, 0, 0, 0, 0, 0, 0, 0, 0, 0, 0, 0, 0, 0, 0, 0, 0, 0, 0, 0, 0, 0, 0, 0, 0, 0, 0, 0, 0, 0, 0, 0, 0, 0, 0, 0, 0, 0, 0, 0, 0, 0, 0, 0, 0, 0, 0, 0, 0, 0, 0, 0, 0, 0, 0, 0, 0, 0, 0, 0, 0, 0, 0, 0, 0, 0, 0, 0, 0, 0, 0, 0, 0, 0, 0, 0, 0, 0, 0, 0, 0, 0, 0, 0, 0, 0, 0, 0, 0, 0, 0, 0, 0, 0, 0, 0, 0, 0, 0, 0, 0, 0, 0, 0, 0, 0, 0, 0, 0, 0, 0, 0, 0, 0, 0, 0, 0, 0, 0, 0, 0, 0, 0, 0, 0, 0, 0, 0, 0, 0, 0, 0, 0, 6062, 6062, 6062, 6062, 6062, 6062, 6062, 6062, 0, 0, 0, 0, 0, 0, 0, 0, 6062, 6062, 6062, 6062, 6062, 6062, 6062, 6062, 0, 0, 0, 0, 0, 0, 0, 0, 0, 0, 0, 0, 0, 0, 0, 0, 0, 0, 0, 0, 0, 0, 0, 0],
         "height":31,
         "id":27,
         "name":"directions",
         "opacity":1,
         "type":"tilelayer",
         "visible":true,
         "width":24,
         "x":0,
         "y":0
        }, 
        {
         "data":[0, 0, 0, 0, 0, 0, 0, 0, 1806, 1807, 1808, 1809, 1807, 1808, 1809, 1810, 0, 0, 0, 0, 0, 0, 0, 0, 0, 0, 0, 0, 0, 0, 0, 0, 1825, 1826, 1827, 1828, 1826, 1827, 1828, 1829, 0, 0, 0, 0, 0, 0, 0, 0, 0, 0, 0, 0, 0, 0, 0, 0, 1844, 1845, 1846, 1847, 1845, 1846, 1847, 1848, 0, 0, 0, 0, 0, 0, 0, 0, 0, 0, 0, 0, 0, 0, 0, 0, 0, 0, 0, 0, 0, 0, 0, 0, 0, 0, 0, 0, 0, 0, 0, 0, 0, 0, 0, 0, 0, 0, 0, 0, 0, 0, 0, 0, 0, 0, 0, 0, 0, 0, 0, 0, 0, 0, 0, 0, 0, 0, 0, 0, 0, 0, 0, 0, 0, 0, 0, 0, 0, 0, 0, 0, 0, 0, 0, 0, 0, 0, 0, 0, 0, 0, 0, 0, 0, 0, 0, 0, 0, 0, 0, 0, 0, 0, 0, 0, 0, 0, 0, 0, 0, 0, 0, 0, 0, 0, 0, 0, 0, 0, 0, 0, 0, 0, 0, 0, 0, 0, 0, 0, 0, 0, 0, 0, 0, 0, 0, 0, 0, 0, 0, 0, 0, 0, 0, 0, 0, 0, 0, 0, 0, 0, 0, 0, 0, 0, 0, 0, 0, 0, 0, 0, 0, 0, 0, 0, 0, 0, 0, 0, 0, 0, 0, 0, 0, 0, 0, 0, 0, 0, 0, 0, 0, 0, 0, 0, 0, 0, 0, 0, 0, 0, 0, 0, 0, 0, 0, 0, 0, 0, 0, 0, 0, 0, 0, 0, 0, 0, 0, 0, 0, 0, 0, 0, 0, 0, 0, 0, 0, 0, 0, 0, 0, 0, 0, 0, 0, 0, 0, 0, 0, 0, 0, 0, 0, 0, 0, 0, 0, 0, 0, 0, 0, 0, 0, 0, 0, 0, 0, 0, 0, 0, 0, 0, 0, 0, 0, 0, 0, 0, 0, 0, 0, 0, 0, 0, 0, 0, 0, 0, 0, 0, 0, 0, 0, 0, 0, 0, 0, 0, 0, 0, 0, 0, 0, 0, 0, 0, 0, 0, 0, 0, 0, 0, 0, 0, 0, 0, 0, 0, 0, 0, 0, 0, 0, 0, 0, 0, 0, 0, 0, 0, 0, 0, 0, 0, 0, 0, 0, 0, 0, 0, 0, 0, 0, 0, 0, 0, 0, 0, 0, 0, 0, 0, 0, 0, 0, 0, 0, 0, 0, 0, 0, 0, 0, 0, 0, 0, 0, 0, 0, 0, 0, 0, 0, 0, 0, 0, 0, 0, 0, 0, 0, 0, 0, 0, 0, 0, 0, 0, 0, 0, 0, 0, 0, 0, 0, 0, 0, 0, 0, 0, 0, 0, 0, 0, 0, 0, 0, 0, 0, 0, 0, 0, 0, 0, 0, 0, 0, 0, 0, 0, 0, 0, 0, 0, 0, 0, 0, 0, 0, 0, 0, 0, 0, 0, 0, 0, 0, 0, 0, 0, 0, 0, 0, 0, 0, 0, 0, 0, 0, 0, 0, 0, 0, 0, 0, 0, 0, 0, 0, 0, 0, 0, 0, 0, 0, 0, 0, 0, 0, 0, 0, 0, 0, 0, 0, 0, 0, 0, 0, 0, 0, 0, 0, 0, 0, 0, 0, 0, 0, 0, 0, 0, 0, 0, 0, 0, 0, 0, 0, 0, 0, 0, 0, 0, 0, 0, 0, 0, 0, 0, 0, 0, 0, 0, 0, 0, 0, 0, 0, 0, 0, 0, 0, 0, 0, 0, 0, 0, 0, 0, 0, 0, 0, 0, 0, 0, 0, 0, 0, 0, 0, 0, 0, 0, 0, 0, 0, 0, 0, 0, 0, 0, 0, 0, 0, 0, 0, 0, 0, 0, 0, 0, 0, 0, 0, 0, 0, 0, 0, 0, 0, 0, 0, 0, 0, 0, 0, 0, 0, 0, 0, 0, 0, 0, 0, 0, 0, 0, 0, 0, 0, 0, 0, 0, 0, 0, 0, 0, 0, 0, 0, 0, 0, 0, 0, 0, 0, 0, 0, 0, 0, 0, 0, 0, 0, 0, 0, 0, 0, 0, 0, 0, 0, 0, 0, 0, 0, 0, 0, 0, 0, 0, 0, 0, 0, 0, 0, 0, 0, 0, 0, 0, 0, 0, 0, 0, 0, 0, 0, 0, 0, 0, 0, 0, 0, 0, 0, 0, 0, 0, 0, 0, 0, 0, 0, 0, 0, 0, 0, 0, 0, 0, 0, 0, 0, 0, 0, 0, 0, 0, 0, 0, 0, 0, 0, 0, 0, 0, 0, 0, 0, 0, 0, 0, 0, 0, 0, 0, 0, 0, 0, 0, 0, 0, 0, 0, 0, 0],
         "height":31,
         "id":43,
         "name":"wall-top",
         "opacity":1,
         "type":"tilelayer",
         "visible":true,
         "width":24,
         "x":0,
         "y":0
        }, 
        {
         "data":[0, 0, 0, 0, 0, 0, 0, 0, 0, 0, 0, 0, 0, 0, 0, 0, 0, 0, 0, 0, 0, 0, 0, 0, 19955, 19956, 0, 0, 0, 0, 0, 0, 0, 1692, 1693, 1694, 1694, 1695, 1696, 0, 0, 0, 0, 0, 0, 0, 19956, 19955, 19968, 19969, 0, 0, 0, 0, 0, 0, 0, 1635, 1712, 1713, 1713, 1714, 1636, 0, 0, 0, 0, 0, 0, 0, 19969, 19968, 0, 0, 0, 0, 0, 0, 0, 0, 0, 1654, 1731, 1732, 1732, 1733, 1655, 0, 0, 0, 0, 0, 0, 0, 0, 0, 0, 0, 2895, 2896, 2895, 2896, 2895, 2896, 2895, 2896, 2895, 2896, 2895, 2896, 2895, 2896, 2895, 2896, 2895, 2896, 2895, 2896, 0, 0, 0, 0, 2914, 2915, 2914, 2915, 2914, 2915, 2914, 2915, 2914, 2915, 2914, 2915, 2914, 2915, 2914, 2915, 2914, 2915, 2914, 2915, 0, 0, 0, 0, 0, 0, 0, 0, 0, 0, 0, 0, 0, 0, 0, 0, 0, 0, 0, 0, 0, 0, 0, 0, 0, 0, 0, 0, 0, 0, 0, 0, 0, 0, 0, 0, 0, 0, 0, 0, 0, 0, 0, 0, 0, 0, 0, 0, 0, 0, 0, 0, 0, 0, 0, 0, 0, 0, 0, 0, 0, 0, 0, 0, 0, 0, 0, 0, 0, 0, 0, 0, 0, 0, 0, 0, 0, 0, 0, 0, 0, 0, 0, 0, 0, 0, 0, 0, 0, 0, 0, 0, 0, 0, 0, 0, 0, 0, 0, 0, 0, 0, 0, 0, 0, 0, 0, 0, 0, 0, 0, 0, 0, 0, 0, 0, 0, 0, 0, 0, 0, 0, 0, 0, 0, 0, 0, 0, 0, 0, 0, 0, 0, 0, 0, 0, 0, 0, 0, 0, 0, 0, 0, 0, 0, 0, 0, 0, 0, 0, 0, 0, 0, 0, 0, 0, 0, 0, 0, 0, 0, 0, 0, 0, 0, 0, 0, 0, 0, 0, 0, 0, 0, 0, 0, 0, 0, 0, 0, 0, 0, 0, 0, 0, 0, 0, 0, 0, 0, 0, 0, 0, 0, 0, 0, 0, 0, 0, 0, 0, 0, 0, 0, 0, 0, 0, 0, 0, 0, 0, 0, 0, 0, 0, 0, 0, 0, 0, 0, 0, 0, 0, 0, 0, 0, 0, 0, 0, 0, 0, 0, 0, 0, 0, 0, 0, 0, 0, 0, 0, 0, 0, 0, 0, 0, 0, 0, 0, 0, 0, 0, 0, 0, 0, 0, 0, 0, 0, 0, 0, 0, 0, 0, 0, 0, 0, 0, 0, 0, 0, 0, 0, 0, 0, 0, 0, 0, 0, 0, 0, 0, 0, 0, 0, 0, 0, 0, 0, 0, 0, 0, 0, 0, 0, 0, 0, 0, 0, 0, 0, 0, 0, 0, 0, 0, 0, 0, 0, 0, 0, 0, 0, 0, 0, 0, 0, 0, 0, 0, 0, 0, 0, 0, 0, 0, 0, 0, 0, 0, 0, 0, 0, 0, 0, 0, 0, 0, 0, 0, 0, 0, 0, 0, 0, 0, 0, 0, 0, 0, 0, 0, 0, 0, 0, 0, 0, 0, 0, 0, 0, 0, 0, 0, 0, 0, 0, 0, 0, 0, 0, 0, 0, 0, 0, 0, 0, 0, 0, 0, 0, 0, 0, 0, 0, 0, 0, 0, 0, 0, 0, 0, 0, 0, 0, 0, 0, 0, 0, 0, 0, 0, 0, 0, 0, 0, 0, 0, 0, 0, 0, 0, 0, 0, 0, 0, 0, 0, 0, 0, 0, 0, 0, 0, 0, 0, 0, 0, 0, 0, 0, 0, 0, 0, 0, 0, 0, 0, 0, 0, 0, 0, 0, 0, 0, 0, 0, 0, 0, 0, 0, 0, 0, 0, 0, 0, 0, 0, 0, 0, 0, 0, 0, 0, 0, 0, 0, 0, 0, 0, 0, 0, 0, 0, 0, 0, 0, 0, 0, 0, 0, 0, 0, 0, 0, 0, 0, 0, 0, 0, 0, 0, 0, 0, 0, 0, 0, 0, 0, 0, 0, 0, 0, 0, 0, 0, 0, 0, 0, 0, 0, 0, 0, 0, 0, 0, 0, 0, 0, 0, 0, 0, 0, 0, 0, 0, 0, 0, 0, 0, 0, 0, 0, 0, 0, 0, 0, 0, 0, 0, 0, 0, 0, 0, 0, 0, 0, 0, 0, 0, 0, 0, 0, 0, 0, 0, 0, 0, 0, 0, 0, 0, 0, 0, 0, 0, 0, 0, 0, 0, 0, 0, 0, 0, 0, 0, 0, 0, 0, 0, 0, 0, 0, 0, 0, 0, 0, 0, 0, 0, 0, 0, 0, 0, 0, 0, 0, 0, 0, 0, 0, 0, 0],
         "height":31,
         "id":23,
         "name":"D\u00e9co",
         "opacity":1,
         "type":"tilelayer",
         "visible":true,
         "width":24,
         "x":0,
         "y":0
        }, 
        {
         "data":[0, 0, 0, 0, 0, 0, 0, 0, 0, 0, 0, 0, 0, 0, 0, 0, 0, 0, 0, 0, 0, 0, 0, 0, 0, 0, 0, 0, 0, 0, 0, 0, 0, 0, 2781, 2782, 2821, 2822, 0, 0, 0, 0, 0, 0, 0, 0, 0, 0, 0, 0, 0, 0, 0, 0, 0, 0, 0, 0, 2800, 2801, 2840, 2841, 0, 0, 0, 0, 0, 0, 0, 0, 0, 0, 0, 0, 0, 0, 0, 0, 0, 0, 0, 0, 0, 0, 0, 0, 0, 0, 0, 0, 0, 0, 0, 0, 0, 0, 0, 0, 0, 0, 0, 0, 0, 0, 0, 0, 0, 0, 0, 0, 0, 0, 0, 0, 0, 0, 0, 0, 0, 0, 0, 0, 13746, 13747, 13746, 13747, 13746, 13747, 13746, 13747, 13746, 13747, 13746, 13747, 13746, 13747, 13746, 13747, 13746, 13747, 13746, 13747, 0, 0, 0, 0, 13765, 13766, 13765, 13766, 13765, 13766, 13765, 13766, 13765, 13766, 13765, 13766, 13765, 13766, 13765, 13766, 13765, 13766, 13765, 13766, 0, 0, 0, 0, 0, 0, 0, 0, 0, 0, 0, 0, 0, 0, 0, 0, 0, 0, 0, 0, 0, 0, 0, 0, 0, 0, 0, 0, 0, 0, 0, 0, 0, 0, 0, 0, 0, 0, 0, 0, 0, 0, 0, 0, 0, 0, 0, 0, 0, 0, 0, 0, 0, 0, 0, 0, 0, 0, 0, 0, 0, 0, 0, 0, 0, 0, 0, 0, 0, 0, 0, 0, 0, 0, 0, 0, 0, 0, 0, 0, 0, 0, 0, 0, 0, 0, 0, 0, 0, 0, 0, 0, 0, 0, 0, 0, 0, 0, 0, 0, 0, 0, 0, 0, 0, 0, 0, 0, 0, 0, 0, 0, 0, 0, 0, 0, 0, 0, 0, 0, 0, 0, 0, 0, 0, 0, 0, 0, 0, 0, 0, 0, 0, 0, 0, 0, 0, 0, 0, 0, 0, 0, 0, 0, 0, 0, 0, 0, 0, 0, 0, 0, 0, 0, 0, 0, 0, 0, 0, 0, 0, 0, 0, 0, 0, 0, 0, 0, 0, 0, 0, 0, 0, 0, 0, 0, 0, 0, 0, 0, 0, 0, 0, 0, 0, 0, 0, 0, 0, 0, 0, 0, 0, 0, 0, 0, 0, 0, 0, 0, 0, 0, 0, 0, 0, 0, 0, 0, 0, 0, 0, 0, 0, 0, 0, 0, 0, 0, 0, 0, 0, 0, 0, 0, 0, 0, 0, 0, 0, 0, 0, 0, 0, 0, 0, 0, 0, 0, 0, 0, 0, 0, 0, 0, 0, 0, 0, 0, 0, 0, 0, 0, 0, 0, 0, 0, 0, 0, 0, 0, 0, 0, 0, 0, 0, 0, 0, 0, 0, 0, 0, 0, 0, 0, 0, 0, 0, 0, 0, 0, 0, 0, 0, 0, 0, 0, 0, 0, 0, 0, 0, 0, 0, 0, 0, 0, 0, 0, 0, 0, 0, 0, 0, 0, 0, 0, 0, 0, 0, 0, 0, 0, 0, 0, 0, 0, 0, 0, 0, 0, 0, 0, 0, 0, 0, 0, 0, 0, 0, 0, 0, 0, 0, 0, 0, 0, 0, 0, 0, 0, 0, 0, 0, 0, 0, 0, 0, 0, 0, 0, 0, 0, 0, 0, 0, 0, 0, 0, 0, 0, 0, 0, 0, 0, 0, 0, 0, 0, 0, 0, 0, 0, 0, 0, 0, 0, 0, 0, 0, 0, 0, 0, 0, 0, 0, 0, 0, 0, 0, 0, 0, 0, 0, 0, 0, 0, 0, 0, 0, 0, 0, 0, 0, 0, 0, 0, 0, 0, 0, 0, 0, 0, 0, 0, 0, 0, 0, 0, 0, 0, 0, 0, 0, 0, 0, 0, 0, 0, 0, 0, 0, 0, 0, 0, 0, 0, 0, 0, 0, 0, 0, 0, 0, 0, 0, 0, 0, 0, 0, 0, 0, 0, 0, 0, 0, 0, 0, 0, 0, 0, 0, 0, 0, 0, 0, 0, 0, 0, 0, 0, 0, 0, 0, 0, 0, 0, 0, 0, 0, 0, 0, 0, 0, 0, 0, 0, 0, 0, 0, 0, 0, 0, 0, 0, 0, 0, 0, 0, 0, 0, 0, 0, 0, 0, 0, 0, 0, 0, 0, 0, 0, 0, 0, 0, 0, 0, 0, 0, 0, 0, 0, 0, 0, 0, 0, 0, 0, 0, 0, 0, 0, 0, 0, 0, 0, 0, 0, 0, 0, 0, 0, 0, 0, 0, 0, 0, 0, 0, 0, 0, 0, 0, 0, 0, 0, 0, 0, 0, 0, 0, 0, 0, 0, 0, 0, 0, 0, 0, 0, 0, 0, 0, 0, 0, 0, 0, 0, 0],
         "height":31,
         "id":28,
         "name":"deco-1",
         "opacity":1,
         "type":"tilelayer",
         "visible":true,
         "width":24,
         "x":0,
         "y":0
        }, 
        {
         "data":[0, 0, 0, 0, 0, 0, 0, 0, 0, 0, 0, 0, 0, 0, 0, 0, 0, 0, 0, 0, 0, 0, 0, 0, 0, 0, 0, 0, 0, 0, 0, 0, 0, 0, 2147491542, 0, 0, 7894, 0, 0, 0, 0, 0, 0, 0, 0, 0, 0, 0, 0, 0, 0, 0, 0, 0, 0, 0, 0, 2147491561, 0, 0, 7913, 0, 0, 0, 0, 0, 0, 0, 0, 0, 0, 0, 0, 0, 0, 0, 0, 0, 0, 0, 0, 0, 0, 0, 0, 0, 0, 0, 0, 0, 0, 0, 0, 0, 0, 0, 0, 0, 0, 0, 0, 0, 0, 0, 0, 0, 0, 0, 0, 0, 0, 0, 0, 0, 0, 0, 0, 0, 0, 0, 0, 0, 0, 0, 0, 0, 0, 0, 0, 0, 0, 0, 0, 0, 0, 0, 0, 0, 0, 0, 0, 0, 0, 0, 0, 2895, 2896, 2895, 2896, 2895, 2896, 2895, 2896, 2895, 2896, 2895, 2896, 2895, 2896, 2895, 2896, 2895, 2896, 2895, 2896, 0, 0, 0, 0, 2914, 2915, 2914, 2915, 2914, 2915, 2914, 2915, 2914, 2915, 2914, 2915, 2914, 2915, 2914, 2915, 2914, 2915, 2914, 2915, 0, 0, 0, 0, 0, 0, 0, 0, 0, 0, 0, 0, 0, 0, 0, 0, 0, 0, 0, 0, 0, 0, 0, 0, 0, 0, 0, 0, 0, 0, 0, 0, 0, 0, 0, 0, 0, 0, 0, 0, 0, 0, 0, 0, 0, 0, 0, 0, 0, 0, 0, 0, 0, 0, 0, 0, 0, 0, 0, 0, 0, 0, 0, 0, 0, 0, 0, 0, 0, 0, 0, 0, 0, 0, 0, 0, 0, 0, 0, 0, 0, 0, 0, 0, 0, 0, 0, 0, 0, 0, 0, 0, 0, 0, 0, 0, 0, 0, 0, 0, 0, 0, 0, 0, 0, 0, 0, 0, 0, 0, 0, 0, 0, 0, 0, 0, 0, 0, 0, 0, 0, 0, 0, 0, 0, 0, 0, 0, 0, 0, 0, 0, 0, 0, 0, 0, 0, 0, 0, 0, 0, 0, 0, 0, 0, 0, 0, 0, 0, 0, 0, 0, 0, 0, 0, 0, 0, 0, 0, 0, 0, 0, 0, 0, 0, 0, 0, 0, 0, 0, 0, 0, 0, 0, 0, 0, 0, 0, 0, 0, 0, 0, 0, 0, 0, 0, 0, 0, 0, 0, 0, 0, 0, 0, 0, 0, 0, 0, 0, 0, 0, 0, 0, 0, 0, 0, 0, 0, 0, 0, 0, 0, 0, 0, 0, 0, 0, 0, 0, 0, 0, 0, 0, 0, 0, 0, 0, 0, 0, 0, 0, 0, 0, 0, 0, 0, 0, 0, 0, 0, 0, 0, 0, 0, 0, 0, 0, 0, 0, 0, 0, 0, 0, 0, 0, 0, 0, 0, 0, 0, 0, 0, 0, 0, 0, 0, 0, 0, 0, 0, 0, 0, 0, 0, 0, 0, 0, 0, 0, 0, 0, 0, 0, 0, 0, 0, 0, 0, 0, 0, 0, 0, 0, 0, 0, 0, 0, 0, 0, 0, 0, 0, 0, 0, 0, 0, 0, 0, 0, 0, 0, 0, 0, 0, 0, 0, 0, 0, 0, 0, 0, 0, 0, 0, 0, 0, 0, 0, 0, 0, 0, 0, 0, 0, 0, 0, 0, 0, 0, 0, 0, 0, 0, 0, 0, 0, 0, 0, 0, 0, 0, 0, 0, 0, 0, 0, 0, 0, 0, 0, 0, 0, 0, 0, 0, 0, 0, 0, 0, 0, 0, 0, 0, 0, 0, 0, 0, 0, 0, 0, 0, 0, 0, 0, 0, 0, 0, 0, 0, 0, 0, 0, 0, 0, 0, 0, 0, 0, 0, 0, 0, 0, 0, 0, 0, 0, 0, 0, 0, 0, 0, 0, 0, 0, 0, 0, 0, 0, 0, 0, 0, 0, 0, 0, 0, 0, 0, 0, 0, 0, 0, 0, 0, 0, 0, 0, 0, 0, 0, 0, 0, 0, 0, 0, 0, 0, 0, 0, 0, 0, 0, 0, 0, 0, 0, 0, 0, 0, 0, 0, 0, 0, 0, 0, 0, 0, 0, 0, 0, 0, 0, 0, 0, 0, 0, 0, 0, 0, 0, 0, 0, 0, 0, 0, 0, 0, 0, 0, 0, 0, 0, 0, 0, 0, 0, 0, 0, 0, 0, 0, 0, 0, 0, 0, 0, 0, 0, 0, 0, 0, 0, 0, 0, 0, 0, 0, 0, 0, 0, 0, 0, 0, 0, 0, 0, 0, 0, 0, 0, 0, 0, 0, 0, 0, 0, 0, 0, 0, 0, 0, 0, 0, 0, 0, 0, 0, 0, 0, 0, 0, 0, 0, 0, 0],
         "height":31,
         "id":29,
         "name":"deco-2",
         "opacity":1,
         "type":"tilelayer",
         "visible":true,
         "width":24,
         "x":0,
         "y":0
        }, 
        {
         "data":[0, 0, 0, 0, 0, 0, 0, 0, 0, 0, 0, 0, 0, 0, 0, 0, 0, 0, 0, 0, 0, 0, 0, 0, 0, 0, 0, 0, 0, 0, 0, 0, 0, 0, 0, 0, 0, 0, 0, 0, 0, 0, 0, 0, 0, 0, 0, 0, 0, 0, 0, 0, 0, 0, 0, 0, 0, 0, 0, 0, 0, 0, 0, 0, 0, 0, 0, 0, 0, 0, 0, 0, 0, 0, 0, 0, 0, 0, 0, 0, 0, 0, 0, 0, 0, 0, 0, 0, 0, 0, 0, 0, 0, 0, 0, 0, 0, 0, 0, 0, 0, 0, 0, 0, 0, 0, 0, 0, 0, 0, 0, 0, 0, 0, 0, 0, 0, 0, 0, 0, 0, 0, 0, 0, 0, 0, 0, 0, 0, 0, 0, 0, 0, 0, 0, 0, 0, 0, 0, 0, 0, 0, 0, 0, 0, 0, 0, 0, 0, 0, 0, 0, 0, 0, 0, 0, 0, 0, 0, 0, 0, 0, 0, 0, 0, 0, 0, 0, 0, 0, 13746, 13747, 13746, 13747, 13746, 13747, 13746, 13747, 13746, 13747, 13746, 13747, 13746, 13747, 13746, 13747, 13746, 13747, 13746, 13747, 0, 0, 0, 0, 13765, 13766, 13765, 13766, 13765, 13766, 13765, 13766, 13765, 13766, 13765, 13766, 13765, 13766, 13765, 13766, 13765, 13766, 13765, 13766, 0, 0, 0, 0, 0, 0, 0, 0, 0, 0, 0, 0, 0, 0, 0, 0, 0, 0, 0, 0, 0, 0, 0, 0, 0, 0, 0, 0, 0, 0, 0, 0, 0, 0, 0, 0, 0, 0, 0, 0, 0, 0, 0, 0, 0, 0, 0, 0, 0, 0, 0, 0, 0, 0, 0, 0, 0, 0, 0, 0, 0, 0, 0, 0, 0, 0, 0, 0, 0, 0, 0, 0, 0, 0, 0, 0, 0, 0, 0, 0, 0, 0, 0, 0, 0, 0, 0, 0, 0, 0, 0, 0, 0, 0, 0, 0, 0, 0, 0, 0, 0, 0, 0, 0, 0, 0, 0, 0, 0, 0, 0, 0, 0, 0, 0, 0, 0, 0, 0, 0, 0, 0, 0, 0, 0, 0, 0, 0, 0, 0, 0, 0, 0, 0, 0, 0, 0, 0, 0, 0, 0, 0, 0, 0, 0, 0, 0, 0, 0, 0, 0, 0, 0, 0, 0, 0, 0, 0, 0, 0, 0, 0, 0, 0, 0, 0, 0, 0, 0, 0, 0, 0, 0, 0, 0, 0, 0, 0, 0, 0, 0, 0, 0, 0, 0, 0, 0, 0, 0, 0, 0, 0, 0, 0, 0, 0, 0, 0, 0, 0, 0, 0, 0, 0, 0, 0, 0, 0, 0, 0, 0, 0, 0, 0, 0, 0, 0, 0, 0, 0, 0, 0, 0, 0, 0, 0, 0, 0, 0, 0, 0, 0, 0, 0, 0, 0, 0, 0, 0, 0, 0, 0, 0, 0, 0, 0, 0, 0, 0, 0, 0, 0, 0, 0, 0, 0, 0, 0, 0, 0, 0, 0, 0, 0, 0, 0, 0, 0, 0, 0, 0, 0, 0, 0, 0, 0, 0, 0, 0, 0, 0, 0, 0, 0, 0, 0, 0, 0, 0, 0, 0, 0, 0, 0, 0, 0, 0, 0, 0, 0, 0, 0, 0, 0, 0, 0, 0, 0, 0, 0, 0, 0, 0, 0, 0, 0, 0, 0, 0, 0, 0, 0, 0, 0, 0, 0, 0, 0, 0, 0, 0, 0, 0, 0, 0, 0, 0, 0, 0, 0, 0, 0, 0, 0, 0, 0, 0, 0, 0, 0, 0, 0, 0, 0, 0, 0, 0, 0, 0, 0, 0, 0, 0, 0, 0, 0, 0, 0, 0, 0, 0, 0, 0, 0, 0, 0, 0, 0, 0, 0, 0, 0, 0, 0, 0, 0, 0, 0, 0, 0, 0, 0, 0, 0, 0, 0, 0, 0, 0, 0, 0, 0, 0, 0, 0, 0, 0, 0, 0, 0, 0, 0, 0, 0, 0, 0, 0, 0, 0, 0, 0, 0, 0, 0, 0, 0, 0, 0, 0, 0, 0, 0, 0, 0, 0, 0, 0, 0, 0, 0, 0, 0, 0, 0, 0, 0, 0, 0, 0, 0, 0, 0, 0, 0, 0, 0, 0, 0, 0, 0, 0, 0, 0, 0, 0, 0, 0, 0, 0, 0, 0, 0, 0, 0, 0, 0, 0, 0, 0, 0, 0, 0, 0, 0, 0, 0, 0, 0, 0, 0, 0, 0, 0, 0, 0, 0, 0, 0, 0, 0, 0, 0, 0, 0, 0, 0, 0, 0, 0, 0, 0, 0, 0, 0, 0, 0, 0, 0, 0, 0, 0, 0, 0, 0, 0, 0, 0, 0, 0, 0],
         "height":31,
         "id":30,
         "name":"deco-3",
         "opacity":1,
         "type":"tilelayer",
         "visible":true,
         "width":24,
         "x":0,
         "y":0
        }, 
        {
         "data":[0, 0, 0, 0, 0, 0, 0, 0, 0, 0, 0, 0, 0, 0, 0, 0, 0, 0, 0, 0, 0, 0, 0, 0, 0, 0, 0, 0, 0, 0, 0, 0, 0, 0, 0, 0, 0, 0, 0, 0, 0, 0, 0, 0, 0, 0, 0, 0, 0, 0, 0, 0, 0, 0, 0, 0, 0, 0, 0, 0, 0, 0, 0, 0, 0, 0, 0, 0, 0, 0, 0, 0, 0, 0, 0, 0, 0, 0, 0, 0, 0, 0, 0, 0, 0, 0, 0, 0, 0, 0, 0, 0, 0, 0, 0, 0, 0, 0, 0, 0, 0, 0, 0, 0, 0, 0, 0, 0, 0, 0, 0, 0, 0, 0, 0, 0, 0, 0, 0, 0, 0, 0, 0, 0, 0, 0, 0, 0, 0, 0, 0, 0, 0, 0, 0, 0, 0, 0, 0, 0, 0, 0, 0, 0, 0, 0, 0, 0, 0, 0, 0, 0, 0, 0, 0, 0, 0, 0, 0, 0, 0, 0, 0, 0, 0, 0, 0, 0, 0, 0, 0, 0, 0, 0, 0, 0, 0, 0, 0, 0, 0, 0, 0, 0, 0, 0, 0, 0, 0, 0, 0, 0, 0, 0, 2895, 2896, 2895, 2896, 2895, 2896, 2895, 2896, 2895, 2896, 2895, 2896, 2895, 2896, 2895, 2896, 2895, 2896, 2895, 2896, 0, 0, 0, 0, 2914, 2915, 2914, 2915, 2914, 2915, 2914, 2915, 2914, 2915, 2914, 2915, 2914, 2915, 2914, 2915, 2914, 2915, 2914, 2915, 0, 0, 0, 0, 0, 0, 0, 0, 0, 0, 0, 0, 0, 0, 0, 0, 0, 0, 0, 0, 0, 0, 0, 0, 0, 0, 0, 0, 0, 0, 0, 0, 0, 0, 0, 0, 0, 0, 0, 0, 0, 0, 0, 0, 0, 0, 0, 0, 0, 0, 0, 0, 0, 0, 0, 0, 0, 0, 0, 0, 0, 0, 0, 0, 0, 0, 0, 0, 0, 0, 0, 0, 0, 0, 0, 0, 0, 0, 0, 0, 0, 0, 0, 0, 0, 0, 0, 0, 0, 0, 0, 0, 0, 0, 0, 0, 0, 0, 0, 0, 0, 0, 0, 0, 0, 0, 0, 0, 0, 0, 0, 0, 0, 0, 0, 0, 0, 0, 0, 0, 0, 0, 0, 0, 0, 0, 0, 0, 0, 0, 0, 0, 0, 0, 0, 0, 0, 0, 0, 0, 0, 0, 0, 0, 0, 0, 0, 0, 0, 0, 0, 0, 0, 0, 0, 0, 0, 0, 0, 0, 0, 0, 0, 0, 0, 0, 0, 0, 0, 0, 0, 0, 2914, 2915, 2914, 2915, 2914, 2915, 2914, 2915, 2914, 2915, 2914, 2915, 2914, 2915, 2914, 2915, 2914, 2915, 2914, 2915, 0, 0, 0, 0, 0, 0, 0, 0, 0, 0, 0, 0, 0, 0, 0, 0, 0, 0, 0, 0, 0, 0, 0, 0, 0, 0, 0, 0, 2914, 2915, 2914, 2915, 2914, 2915, 2914, 2915, 2914, 2915, 2914, 2915, 2914, 2915, 2914, 2915, 2914, 2915, 2914, 2915, 0, 0, 0, 0, 0, 0, 0, 0, 0, 0, 0, 0, 0, 0, 0, 0, 0, 0, 0, 0, 0, 0, 0, 0, 0, 0, 0, 0, 0, 0, 0, 0, 0, 0, 0, 0, 0, 0, 0, 0, 0, 0, 0, 0, 0, 0, 0, 0, 0, 0, 0, 0, 0, 0, 0, 0, 0, 0, 0, 0, 0, 0, 0, 0, 0, 0, 0, 0, 0, 0, 0, 0, 0, 0, 0, 0, 0, 0, 0, 0, 0, 0, 0, 0, 0, 0, 0, 0, 0, 0, 0, 0, 0, 0, 0, 0, 0, 0, 0, 0, 0, 0, 0, 0, 0, 0, 0, 0, 0, 0, 0, 0, 0, 0, 0, 0, 0, 0, 0, 0, 0, 0, 0, 0, 0, 0, 0, 0, 0, 0, 0, 0, 0, 0, 0, 0, 0, 0, 0, 0, 0, 0, 0, 0, 0, 0, 0, 0, 0, 0, 0, 0, 0, 0, 0, 0, 0, 0, 0, 0, 0, 0, 0, 0, 0, 0, 0, 0, 0, 0, 0, 0, 0, 0, 0, 0, 0, 0, 0, 0, 0, 0, 0, 0, 0, 0, 0, 0, 0, 0, 0, 0, 0, 0, 0, 0, 0, 0, 0, 0, 0, 0, 0, 0, 0, 0, 0, 0, 0, 0, 0, 0, 0, 0, 0, 0, 0, 0, 0, 0, 0, 0, 0, 0, 0, 0, 0, 0, 0, 0, 0, 0, 0, 0, 0, 0, 0, 0, 0, 0, 0, 0, 0, 0, 0, 0, 0, 0, 0, 0, 0, 0, 0, 0, 0, 0, 0, 0, 0, 0, 0, 0, 0, 0, 0, 0],
         "height":31,
         "id":31,
         "name":"deco-4",
         "opacity":1,
         "type":"tilelayer",
         "visible":true,
         "width":24,
         "x":0,
         "y":0
        }, 
        {
         "data":[0, 0, 0, 0, 0, 0, 0, 0, 0, 0, 0, 0, 0, 0, 0, 0, 0, 0, 0, 0, 0, 0, 0, 0, 0, 0, 0, 0, 0, 0, 0, 0, 0, 0, 0, 0, 0, 0, 0, 0, 0, 0, 0, 0, 0, 0, 0, 0, 0, 0, 0, 0, 0, 0, 0, 0, 0, 0, 0, 0, 0, 0, 0, 0, 0, 0, 0, 0, 0, 0, 0, 0, 0, 0, 0, 0, 0, 0, 0, 0, 0, 0, 0, 0, 0, 0, 0, 0, 0, 0, 0, 0, 0, 0, 0, 0, 0, 0, 0, 0, 0, 0, 0, 0, 0, 0, 0, 0, 0, 0, 0, 0, 0, 0, 0, 0, 0, 0, 0, 0, 0, 0, 0, 0, 0, 0, 0, 0, 0, 0, 0, 0, 0, 0, 0, 0, 0, 0, 0, 0, 0, 0, 0, 0, 0, 0, 0, 0, 0, 0, 0, 0, 0, 0, 0, 0, 0, 0, 0, 0, 0, 0, 0, 0, 0, 0, 0, 0, 0, 0, 0, 0, 0, 0, 0, 0, 0, 0, 0, 0, 0, 0, 0, 0, 0, 0, 0, 0, 0, 0, 0, 0, 0, 0, 0, 0, 0, 0, 0, 0, 0, 0, 0, 0, 0, 0, 0, 0, 0, 0, 0, 0, 0, 0, 0, 0, 0, 0, 13746, 13747, 13746, 13747, 13746, 13747, 13746, 13747, 13746, 13747, 13746, 13747, 13746, 13747, 13746, 13747, 13746, 13747, 13746, 13747, 0, 0, 0, 0, 13765, 13766, 13765, 13766, 13765, 13766, 13765, 13766, 13765, 13766, 13765, 13766, 13765, 13766, 13765, 13766, 13765, 13766, 13765, 13766, 0, 0, 0, 0, 0, 0, 0, 0, 0, 0, 0, 0, 0, 0, 0, 0, 0, 0, 0, 0, 0, 0, 0, 0, 0, 0, 0, 0, 0, 0, 0, 0, 0, 0, 0, 0, 0, 0, 0, 0, 0, 0, 0, 0, 0, 0, 0, 0, 0, 0, 0, 0, 0, 0, 0, 0, 0, 0, 0, 0, 0, 0, 0, 0, 0, 0, 0, 0, 0, 0, 0, 0, 0, 0, 0, 0, 0, 0, 0, 0, 0, 0, 0, 0, 0, 0, 0, 0, 0, 0, 0, 0, 0, 0, 0, 0, 0, 0, 0, 0, 0, 0, 0, 0, 0, 0, 0, 0, 0, 0, 0, 0, 0, 0, 0, 0, 0, 0, 0, 0, 0, 0, 0, 0, 0, 0, 0, 0, 0, 0, 0, 0, 0, 0, 0, 0, 0, 0, 0, 0, 0, 0, 0, 0, 0, 0, 0, 0, 13746, 13747, 13746, 13747, 13746, 13747, 13746, 13747, 13746, 13747, 13746, 13747, 13746, 13747, 13746, 13747, 13746, 13747, 13746, 13747, 0, 0, 0, 0, 13765, 13766, 13765, 13766, 13765, 13766, 13765, 13766, 13765, 13766, 13765, 13766, 13765, 13766, 13765, 13766, 13765, 13766, 13765, 13766, 0, 0, 0, 0, 13746, 13747, 13746, 13747, 13746, 13747, 13746, 13747, 13746, 13747, 13746, 13747, 13746, 13747, 13746, 13747, 13746, 13747, 13746, 13747, 0, 0, 0, 0, 13765, 13766, 13765, 13766, 13765, 13766, 13765, 13766, 13765, 13766, 13765, 13766, 13765, 13766, 13765, 13766, 13765, 13766, 13765, 13766, 0, 0, 0, 0, 0, 0, 0, 0, 0, 0, 0, 0, 0, 0, 0, 0, 0, 0, 0, 0, 0, 0, 0, 0, 0, 0, 0, 0, 0, 0, 0, 0, 0, 0, 0, 0, 0, 0, 0, 0, 0, 0, 0, 0, 0, 0, 0, 0, 0, 0, 0, 0, 0, 0, 0, 0, 0, 0, 0, 0, 0, 0, 0, 0, 0, 0, 0, 0, 0, 0, 0, 0, 0, 0, 0, 0, 0, 0, 0, 0, 0, 0, 0, 0, 0, 0, 0, 0, 0, 0, 0, 0, 0, 0, 0, 0, 0, 0, 0, 0, 0, 0, 0, 0, 0, 0, 0, 0, 0, 0, 0, 0, 0, 0, 0, 0, 0, 0, 0, 0, 0, 0, 0, 0, 0, 0, 0, 0, 0, 0, 0, 0, 0, 0, 0, 0, 0, 0, 0, 0, 0, 0, 0, 0, 0, 0, 0, 0, 0, 0, 0, 0, 0, 0, 0, 0, 0, 0, 0, 0, 0, 0, 0, 0, 0, 0, 0, 0, 0, 0, 0, 0, 0, 0, 0, 0, 0, 0, 0, 0, 0, 0, 0, 0, 0, 0, 0, 0, 0, 0, 0, 0, 0, 0, 0, 0, 0, 0, 0, 0, 0, 0, 0, 0, 0, 0, 0, 0, 0, 0, 0, 0, 0, 0, 0, 0, 0, 0, 0, 0, 0, 0, 0, 0, 0, 0, 0, 0, 0, 0, 0, 0, 0, 0, 0, 0, 0, 0, 0, 0, 0, 0],
         "height":31,
         "id":32,
         "name":"deco-5",
         "opacity":1,
         "type":"tilelayer",
         "visible":true,
         "width":24,
         "x":0,
         "y":0
        }, 
        {
         "data":[0, 0, 0, 0, 0, 0, 0, 0, 0, 0, 0, 0, 0, 0, 0, 0, 0, 0, 0, 0, 0, 0, 0, 0, 0, 0, 0, 0, 0, 0, 0, 0, 0, 0, 0, 0, 0, 0, 0, 0, 0, 0, 0, 0, 0, 0, 0, 0, 0, 0, 0, 0, 0, 0, 0, 0, 0, 0, 0, 0, 0, 0, 0, 0, 0, 0, 0, 0, 0, 0, 0, 0, 0, 0, 0, 0, 0, 0, 0, 0, 0, 0, 0, 0, 0, 0, 0, 0, 0, 0, 0, 0, 0, 0, 0, 0, 0, 0, 0, 0, 0, 0, 0, 0, 0, 0, 0, 0, 0, 0, 0, 0, 0, 0, 0, 0, 0, 0, 0, 0, 0, 0, 0, 0, 0, 0, 0, 0, 0, 0, 0, 0, 0, 0, 0, 0, 0, 0, 0, 0, 0, 0, 0, 0, 0, 0, 0, 0, 0, 0, 0, 0, 0, 0, 0, 0, 0, 0, 0, 0, 0, 0, 0, 0, 0, 0, 0, 0, 0, 0, 0, 0, 0, 0, 0, 0, 0, 0, 0, 0, 0, 0, 0, 0, 0, 0, 0, 0, 0, 0, 0, 0, 0, 0, 0, 0, 0, 0, 0, 0, 0, 0, 0, 0, 0, 0, 0, 0, 0, 0, 0, 0, 0, 0, 0, 0, 0, 0, 0, 0, 0, 0, 0, 0, 0, 0, 0, 0, 0, 0, 0, 0, 0, 0, 0, 0, 0, 0, 0, 0, 0, 0, 2895, 2896, 2895, 2896, 2895, 2896, 2895, 2896, 2895, 2896, 2895, 2896, 2895, 2896, 2895, 2896, 2895, 2896, 2895, 2896, 0, 0, 0, 0, 2914, 2915, 2914, 2915, 2914, 2915, 2914, 2915, 2914, 2915, 2914, 2915, 2914, 2915, 2914, 2915, 2914, 2915, 2914, 2915, 0, 0, 0, 0, 0, 0, 0, 0, 0, 0, 0, 0, 0, 0, 0, 0, 0, 0, 0, 0, 0, 0, 0, 0, 0, 0, 0, 0, 0, 0, 0, 0, 0, 0, 0, 0, 0, 0, 0, 0, 0, 0, 0, 0, 0, 0, 0, 0, 0, 0, 0, 0, 0, 0, 0, 0, 0, 0, 0, 0, 0, 0, 0, 0, 0, 0, 0, 0, 0, 0, 0, 0, 0, 0, 0, 0, 0, 0, 0, 0, 0, 0, 0, 0, 0, 0, 0, 0, 0, 0, 0, 0, 0, 0, 0, 0, 0, 0, 0, 0, 0, 0, 0, 0, 0, 0, 0, 0, 0, 0, 0, 0, 0, 0, 0, 0, 0, 0, 0, 0, 0, 0, 0, 0, 0, 0, 0, 0, 0, 0, 0, 0, 0, 0, 0, 0, 0, 0, 0, 0, 0, 0, 0, 0, 0, 0, 0, 0, 2895, 2896, 2895, 2896, 2895, 2896, 2895, 2896, 2895, 2896, 2895, 2896, 2895, 2896, 2895, 2896, 2895, 2896, 2895, 2896, 0, 0, 0, 0, 0, 0, 0, 0, 0, 0, 0, 0, 0, 0, 0, 0, 0, 0, 0, 0, 0, 0, 0, 0, 0, 0, 0, 0, 2895, 2896, 2895, 2896, 2895, 2896, 2895, 2896, 2895, 2896, 2895, 2896, 2895, 2896, 2895, 2896, 2895, 2896, 2895, 2896, 0, 0, 0, 0, 2914, 2915, 2914, 2915, 2914, 2915, 2914, 2915, 2914, 2915, 2914, 2915, 2914, 2915, 2914, 2915, 2914, 2915, 2914, 2915, 0, 0, 0, 0, 0, 0, 0, 0, 0, 0, 0, 0, 0, 0, 0, 0, 0, 0, 0, 0, 0, 0, 0, 0, 0, 0, 0, 0, 0, 0, 0, 0, 0, 0, 0, 0, 0, 0, 0, 0, 0, 0, 0, 0, 0, 0, 0, 0, 0, 0, 0, 0, 0, 0, 0, 0, 0, 0, 0, 0, 0, 0, 0, 0, 0, 0, 0, 0, 0, 0, 0, 0, 0, 0, 0, 0, 0, 0, 0, 0, 0, 0, 0, 0, 0, 0, 0, 0, 0, 0, 0, 0, 0, 0, 0, 0, 0, 0, 0, 0, 0, 0, 0, 0, 0, 0, 0, 0, 0, 0, 0, 0, 0, 0, 0, 0, 0, 0, 0, 0, 0, 0, 0, 0, 0, 0, 0, 0, 0, 0, 0, 0, 0, 0, 0, 0, 0, 0, 0, 0, 0, 0, 0, 0, 0, 0, 0, 0, 0, 0, 0, 0, 0, 0, 0, 0, 0, 0, 0, 0, 0, 0, 0, 0, 0, 0, 0, 0, 0, 0, 0, 0, 0, 0, 0, 0, 0, 0, 0, 0, 0, 0, 0, 0, 0, 0, 0, 0, 0, 0, 0, 0, 0, 0, 0, 0, 0, 0, 0, 0, 0, 0, 0, 0, 0, 0, 0, 0, 0, 0, 0, 0, 0, 0, 0, 0, 0, 0],
         "height":31,
         "id":33,
         "name":"deco-6",
         "opacity":1,
         "type":"tilelayer",
         "visible":true,
         "width":24,
         "x":0,
         "y":0
        }, 
        {
         "data":[0, 0, 0, 0, 0, 0, 0, 0, 0, 0, 0, 0, 0, 0, 0, 0, 0, 0, 0, 0, 0, 0, 0, 0, 0, 0, 0, 0, 0, 0, 0, 0, 0, 0, 0, 0, 0, 0, 0, 0, 0, 0, 0, 0, 0, 0, 0, 0, 0, 0, 0, 0, 0, 0, 0, 0, 0, 0, 0, 0, 0, 0, 0, 0, 0, 0, 0, 0, 0, 0, 0, 0, 0, 0, 0, 0, 0, 0, 0, 0, 0, 0, 0, 0, 0, 0, 0, 0, 0, 0, 0, 0, 0, 0, 0, 0, 0, 0, 0, 0, 0, 0, 0, 0, 0, 0, 0, 0, 0, 0, 0, 0, 0, 0, 0, 0, 0, 0, 0, 0, 0, 0, 0, 0, 0, 0, 0, 0, 0, 0, 0, 0, 0, 0, 0, 0, 0, 0, 0, 0, 0, 0, 0, 0, 0, 0, 0, 0, 0, 0, 0, 0, 0, 0, 0, 0, 0, 0, 0, 0, 0, 0, 0, 0, 0, 0, 0, 0, 0, 0, 0, 0, 0, 0, 0, 0, 0, 0, 0, 0, 0, 0, 0, 0, 0, 0, 0, 0, 0, 0, 0, 0, 0, 0, 0, 0, 0, 0, 0, 0, 0, 0, 0, 0, 0, 0, 0, 0, 0, 0, 0, 0, 0, 0, 0, 0, 0, 0, 0, 0, 0, 0, 0, 0, 0, 0, 0, 0, 0, 0, 0, 0, 0, 0, 0, 0, 0, 0, 0, 0, 0, 0, 0, 0, 0, 0, 0, 0, 0, 0, 0, 0, 0, 0, 0, 0, 0, 0, 0, 0, 0, 0, 0, 0, 0, 0, 13746, 13747, 13746, 13747, 13746, 13747, 13746, 13747, 13746, 13747, 13746, 13747, 13746, 13747, 13746, 13747, 13746, 13747, 13746, 13747, 0, 0, 0, 0, 13765, 13766, 13765, 13766, 13765, 13766, 13765, 13766, 13765, 13766, 13765, 13766, 13765, 13766, 13765, 13766, 13765, 13766, 13765, 13766, 0, 0, 0, 0, 0, 0, 0, 0, 0, 0, 0, 0, 0, 0, 0, 0, 0, 0, 0, 0, 0, 0, 0, 0, 0, 0, 0, 0, 0, 0, 0, 0, 0, 0, 0, 0, 0, 0, 0, 0, 0, 0, 0, 0, 0, 0, 0, 0, 0, 0, 0, 0, 0, 0, 0, 0, 0, 0, 0, 0, 0, 0, 0, 0, 0, 0, 0, 0, 0, 0, 0, 0, 0, 0, 0, 0, 0, 0, 0, 0, 0, 0, 0, 0, 0, 0, 0, 0, 0, 0, 0, 0, 0, 0, 0, 0, 0, 0, 0, 0, 0, 0, 0, 0, 0, 0, 0, 0, 0, 0, 0, 0, 0, 0, 0, 0, 0, 0, 0, 0, 0, 0, 0, 0, 0, 0, 0, 0, 0, 0, 0, 0, 0, 0, 0, 0, 0, 0, 0, 0, 0, 0, 0, 0, 0, 0, 0, 0, 0, 0, 0, 0, 0, 0, 0, 0, 0, 0, 0, 0, 0, 0, 0, 0, 0, 0, 0, 0, 0, 0, 0, 0, 0, 0, 0, 0, 0, 0, 0, 0, 0, 0, 0, 0, 0, 0, 0, 0, 0, 0, 0, 0, 0, 0, 0, 0, 13746, 13747, 13746, 13747, 13746, 13747, 13746, 13747, 13746, 13747, 13746, 13747, 13746, 13747, 13746, 13747, 13746, 13747, 13746, 13747, 0, 0, 0, 0, 13765, 13766, 13765, 13766, 13765, 13766, 13765, 13766, 13765, 13766, 13765, 13766, 13765, 13766, 13765, 13766, 13765, 13766, 13765, 13766, 0, 0, 0, 0, 0, 0, 0, 0, 0, 0, 0, 0, 0, 0, 0, 0, 0, 0, 0, 0, 0, 0, 0, 0, 0, 0, 0, 0, 0, 0, 0, 0, 0, 0, 0, 0, 0, 0, 0, 0, 0, 0, 0, 0, 0, 0, 0, 0, 0, 0, 0, 0, 0, 0, 0, 0, 0, 0, 0, 0, 0, 0, 0, 0, 0, 0, 0, 0, 0, 0, 0, 0, 0, 0, 0, 0, 0, 0, 0, 0, 0, 0, 0, 0, 0, 0, 0, 0, 0, 0, 0, 0, 0, 0, 0, 0, 0, 0, 0, 0, 0, 0, 0, 0, 0, 0, 0, 0, 0, 0, 0, 0, 0, 0, 0, 0, 0, 0, 0, 0, 0, 0, 0, 0, 0, 0, 0, 0, 0, 0, 0, 0, 0, 0, 0, 0, 0, 0, 0, 0, 0, 0, 0, 0, 0, 0, 0, 0, 0, 0, 0, 0, 0, 0, 0, 0, 0, 0, 0, 0, 0, 0, 0, 0, 0, 0, 0, 0, 0, 0, 0, 0, 0, 0, 0, 0, 0, 0, 0, 0, 0, 0, 0, 0, 0, 0, 0, 0, 0, 0, 0, 0, 0, 0],
         "height":31,
         "id":34,
         "name":"deco-7",
         "opacity":1,
         "type":"tilelayer",
         "visible":true,
         "width":24,
         "x":0,
         "y":0
        }, 
        {
         "data":[0, 0, 0, 0, 0, 0, 0, 0, 0, 0, 0, 0, 0, 0, 0, 0, 0, 0, 0, 0, 0, 0, 0, 0, 0, 0, 0, 0, 0, 0, 0, 0, 0, 0, 0, 0, 0, 0, 0, 0, 0, 0, 0, 0, 0, 0, 0, 0, 0, 0, 0, 0, 0, 0, 0, 0, 0, 0, 0, 0, 0, 0, 0, 0, 0, 0, 0, 0, 0, 0, 0, 0, 0, 0, 0, 0, 0, 0, 0, 0, 0, 0, 0, 0, 0, 0, 0, 0, 0, 0, 0, 0, 0, 0, 0, 0, 0, 0, 0, 0, 0, 0, 0, 0, 0, 0, 0, 0, 0, 0, 0, 0, 0, 0, 0, 0, 0, 0, 0, 0, 0, 0, 0, 0, 0, 0, 0, 0, 0, 0, 0, 0, 0, 0, 0, 0, 0, 0, 0, 0, 0, 0, 0, 0, 0, 0, 0, 0, 0, 0, 0, 0, 0, 0, 0, 0, 0, 0, 0, 0, 0, 0, 0, 0, 0, 0, 0, 0, 0, 0, 0, 0, 0, 0, 0, 0, 0, 0, 0, 0, 0, 0, 0, 0, 0, 0, 0, 0, 0, 0, 0, 0, 0, 0, 0, 0, 0, 0, 0, 0, 0, 0, 0, 0, 0, 0, 0, 0, 0, 0, 0, 0, 0, 0, 0, 0, 0, 0, 0, 0, 0, 0, 0, 0, 0, 0, 0, 0, 0, 0, 0, 0, 0, 0, 0, 0, 0, 0, 0, 0, 0, 0, 0, 0, 0, 0, 0, 0, 0, 0, 0, 0, 0, 0, 0, 0, 0, 0, 0, 0, 0, 0, 0, 0, 0, 0, 0, 0, 0, 0, 0, 0, 0, 0, 0, 0, 0, 0, 0, 0, 0, 0, 0, 0, 0, 0, 0, 0, 0, 0, 2895, 2896, 2895, 2896, 2895, 2896, 2895, 2896, 2895, 2896, 2895, 2896, 2895, 2896, 2895, 2896, 2895, 2896, 2895, 2896, 0, 0, 0, 0, 2914, 2915, 2914, 2915, 2914, 2915, 2914, 2915, 2914, 2915, 2914, 2915, 2914, 2915, 2914, 2915, 2914, 2915, 2914, 2915, 0, 0, 0, 0, 0, 0, 0, 0, 0, 0, 0, 0, 0, 0, 0, 0, 0, 0, 0, 0, 0, 0, 0, 0, 0, 0, 0, 0, 0, 0, 0, 0, 0, 0, 0, 0, 0, 0, 0, 0, 0, 0, 0, 0, 0, 0, 0, 0, 0, 0, 0, 0, 0, 0, 0, 0, 0, 0, 0, 0, 0, 0, 0, 0, 0, 0, 0, 0, 0, 0, 0, 0, 0, 0, 0, 0, 0, 0, 0, 0, 0, 0, 0, 0, 0, 0, 0, 0, 0, 0, 0, 0, 0, 0, 0, 0, 0, 0, 0, 0, 0, 0, 0, 0, 0, 0, 0, 0, 0, 0, 0, 0, 0, 0, 0, 0, 0, 0, 0, 0, 0, 0, 0, 0, 0, 0, 0, 0, 0, 0, 0, 0, 0, 0, 0, 0, 0, 0, 0, 0, 0, 0, 0, 0, 0, 0, 0, 0, 0, 0, 0, 0, 0, 0, 0, 0, 0, 0, 0, 0, 0, 0, 0, 0, 0, 0, 0, 0, 0, 0, 0, 0, 0, 0, 0, 0, 0, 0, 0, 0, 0, 0, 0, 0, 0, 0, 0, 0, 0, 0, 0, 0, 0, 0, 0, 0, 2895, 2896, 2895, 2896, 2895, 2896, 2895, 2896, 2895, 2896, 2895, 2896, 2895, 2896, 2895, 2896, 2895, 2896, 2895, 2896, 0, 0, 0, 0, 2914, 2915, 2914, 2915, 2914, 2915, 2914, 2915, 2914, 2915, 2914, 2915, 2914, 2915, 2914, 2915, 2914, 2915, 2914, 2915, 0, 0, 0, 0, 0, 0, 0, 0, 0, 0, 0, 0, 0, 0, 0, 0, 0, 0, 0, 0, 0, 0, 0, 0, 0, 0, 0, 0, 0, 0, 0, 0, 0, 0, 0, 0, 0, 0, 0, 0, 0, 0, 0, 0, 0, 0, 0, 0, 0, 0, 0, 0, 0, 0, 0, 0, 0, 0, 0, 0, 0, 0, 0, 0, 0, 0, 0, 0, 0, 0, 0, 0, 0, 0, 0, 0, 0, 0, 0, 0, 0, 0, 0, 0, 0, 0, 0, 0, 0, 0, 0, 0, 0, 0, 0, 0, 0, 0, 0, 0, 0, 0, 0, 0, 0, 0, 0, 0, 0, 0, 0, 0, 0, 0, 0, 0, 0, 0, 0, 0, 0, 0, 0, 0, 0, 0, 0, 0, 0, 0, 0, 0, 0, 0, 0, 0, 0, 0, 0, 0, 0, 0, 0, 0, 0, 0, 0, 0, 0, 0, 0, 0, 0, 0, 0, 0, 0, 0, 0, 0, 0, 0, 0, 0, 0, 0, 0, 0, 0, 0],
         "height":31,
         "id":35,
         "name":"deco-8",
         "opacity":1,
         "type":"tilelayer",
         "visible":true,
         "width":24,
         "x":0,
         "y":0
        }, 
        {
         "data":[0, 0, 0, 0, 0, 0, 0, 0, 0, 0, 0, 0, 0, 0, 0, 0, 0, 0, 0, 0, 0, 0, 0, 0, 0, 0, 0, 0, 0, 0, 0, 0, 0, 0, 0, 0, 0, 0, 0, 0, 0, 0, 0, 0, 0, 0, 0, 0, 0, 0, 0, 0, 0, 0, 0, 0, 0, 0, 0, 0, 0, 0, 0, 0, 0, 0, 0, 0, 0, 0, 0, 0, 0, 0, 0, 0, 0, 0, 0, 0, 0, 0, 0, 0, 0, 0, 0, 0, 0, 0, 0, 0, 0, 0, 0, 0, 0, 0, 0, 0, 0, 0, 0, 0, 0, 0, 0, 0, 0, 0, 0, 0, 0, 0, 0, 0, 0, 0, 0, 0, 0, 0, 0, 0, 0, 0, 0, 0, 0, 0, 0, 0, 0, 0, 0, 0, 0, 0, 0, 0, 0, 0, 0, 0, 0, 0, 0, 0, 0, 0, 0, 0, 0, 0, 0, 0, 0, 0, 0, 0, 0, 0, 0, 0, 0, 0, 0, 0, 0, 0, 0, 0, 0, 0, 0, 0, 0, 0, 0, 0, 0, 0, 0, 0, 0, 0, 0, 0, 0, 0, 0, 0, 0, 0, 0, 0, 0, 0, 0, 0, 0, 0, 0, 0, 0, 0, 0, 0, 0, 0, 0, 0, 0, 0, 0, 0, 0, 0, 0, 0, 0, 0, 0, 0, 0, 0, 0, 0, 0, 0, 0, 0, 0, 0, 0, 0, 0, 0, 0, 0, 0, 0, 0, 0, 0, 0, 0, 0, 0, 0, 0, 0, 0, 0, 0, 0, 0, 0, 0, 0, 0, 0, 0, 0, 0, 0, 0, 0, 0, 0, 0, 0, 0, 0, 0, 0, 0, 0, 0, 0, 0, 0, 0, 0, 0, 0, 0, 0, 0, 0, 0, 0, 0, 0, 0, 0, 0, 0, 0, 0, 0, 0, 0, 0, 0, 0, 0, 0, 0, 0, 0, 0, 0, 0, 13746, 13747, 13746, 13747, 13746, 13747, 13746, 13747, 13746, 13747, 13746, 13747, 13746, 13747, 13746, 13747, 13746, 13747, 13746, 13747, 0, 0, 0, 0, 13765, 13766, 13765, 13766, 13765, 13766, 13765, 13766, 13765, 13766, 13765, 13766, 13765, 13766, 13765, 13766, 13765, 13766, 13765, 13766, 0, 0, 0, 0, 0, 0, 0, 0, 0, 0, 0, 0, 0, 0, 0, 0, 0, 0, 0, 0, 0, 0, 0, 0, 0, 0, 0, 0, 0, 0, 0, 0, 0, 0, 0, 0, 0, 0, 0, 0, 0, 0, 0, 0, 0, 0, 0, 0, 0, 0, 0, 0, 0, 0, 0, 0, 0, 0, 0, 0, 0, 0, 0, 0, 0, 0, 0, 0, 0, 0, 0, 0, 0, 0, 0, 0, 0, 0, 0, 0, 0, 0, 0, 0, 0, 0, 0, 0, 0, 0, 0, 0, 0, 0, 0, 0, 0, 0, 0, 0, 0, 0, 0, 0, 0, 0, 0, 0, 0, 0, 0, 0, 0, 0, 0, 0, 0, 0, 0, 0, 0, 0, 0, 0, 0, 0, 0, 0, 0, 0, 0, 0, 0, 0, 0, 0, 0, 0, 0, 0, 0, 0, 0, 0, 0, 0, 0, 0, 0, 0, 0, 0, 0, 0, 0, 0, 0, 0, 0, 0, 0, 0, 0, 0, 0, 0, 0, 0, 0, 0, 0, 0, 0, 0, 0, 0, 0, 0, 0, 0, 0, 0, 0, 0, 0, 0, 0, 0, 0, 0, 0, 0, 0, 0, 0, 0, 13746, 13747, 13746, 13747, 13746, 13747, 13746, 13747, 13746, 13747, 13746, 13747, 13746, 13747, 13746, 13747, 13746, 13747, 13746, 13747, 0, 0, 0, 0, 13765, 13766, 13765, 13766, 13765, 13766, 13765, 13766, 13765, 13766, 13765, 13766, 13765, 13766, 13765, 13766, 13765, 13766, 13765, 13766, 0, 0, 0, 0, 0, 0, 0, 0, 0, 0, 0, 0, 0, 0, 0, 0, 0, 0, 0, 0, 0, 0, 0, 0, 0, 0, 0, 0, 0, 0, 0, 0, 0, 0, 0, 0, 0, 0, 0, 0, 0, 0, 0, 0, 0, 0, 0, 0, 0, 0, 0, 0, 0, 0, 0, 0, 0, 0, 0, 0, 0, 0, 0, 0, 0, 0, 0, 0, 0, 0, 0, 0, 0, 0, 0, 0, 0, 0, 0, 0, 0, 0, 0, 0, 0, 0, 0, 0, 0, 0, 0, 0, 0, 0, 0, 0, 0, 0, 0, 0, 0, 0, 0, 0, 0, 0, 0, 0, 0, 0, 0, 0, 0, 0, 0, 0, 0, 0, 0, 0, 0, 0, 0, 0, 0, 0, 0, 0, 0, 0, 0, 0, 0, 0, 0, 0, 0, 0, 0, 0, 0, 0, 0, 0, 0, 0],
         "height":31,
         "id":36,
         "name":"deco-9",
         "opacity":1,
         "type":"tilelayer",
         "visible":true,
         "width":24,
         "x":0,
         "y":0
        }, 
        {
         "data":[0, 0, 0, 0, 0, 0, 0, 0, 0, 0, 0, 0, 0, 0, 0, 0, 0, 0, 0, 0, 0, 0, 0, 0, 0, 0, 0, 0, 0, 0, 0, 0, 0, 0, 0, 0, 0, 0, 0, 0, 0, 0, 0, 0, 0, 0, 0, 0, 0, 0, 0, 0, 0, 0, 0, 0, 0, 0, 0, 0, 0, 0, 0, 0, 0, 0, 0, 0, 0, 0, 0, 0, 0, 0, 0, 0, 0, 0, 0, 0, 0, 0, 0, 0, 0, 0, 0, 0, 0, 0, 0, 0, 0, 0, 0, 0, 0, 0, 0, 0, 0, 0, 0, 0, 0, 0, 0, 0, 0, 0, 0, 0, 0, 0, 0, 0, 0, 0, 0, 0, 0, 0, 0, 0, 0, 0, 0, 0, 0, 0, 0, 0, 0, 0, 0, 0, 0, 0, 0, 0, 0, 0, 0, 0, 0, 0, 0, 0, 0, 0, 0, 0, 0, 0, 0, 0, 0, 0, 0, 0, 0, 0, 0, 0, 0, 0, 0, 0, 0, 0, 0, 0, 0, 0, 0, 0, 0, 0, 0, 0, 0, 0, 0, 0, 0, 0, 0, 0, 0, 0, 0, 0, 0, 0, 0, 0, 0, 0, 0, 0, 0, 0, 0, 0, 0, 0, 0, 0, 0, 0, 0, 0, 0, 0, 0, 0, 0, 0, 0, 0, 0, 0, 0, 0, 0, 0, 0, 0, 0, 0, 0, 0, 0, 0, 0, 0, 0, 0, 0, 0, 0, 0, 0, 0, 0, 0, 0, 0, 0, 0, 0, 0, 0, 0, 0, 0, 0, 0, 0, 0, 0, 0, 0, 0, 0, 0, 0, 0, 0, 0, 0, 0, 0, 0, 0, 0, 0, 0, 0, 0, 0, 0, 0, 0, 0, 0, 0, 0, 0, 0, 0, 0, 0, 0, 0, 0, 0, 0, 0, 0, 0, 0, 0, 0, 0, 0, 0, 0, 0, 0, 0, 0, 0, 0, 0, 0, 0, 0, 0, 0, 0, 0, 0, 0, 0, 0, 0, 0, 0, 0, 0, 0, 0, 0, 0, 0, 0, 0, 2895, 2896, 2895, 2896, 2895, 2896, 2895, 2896, 2895, 2896, 2895, 2896, 2895, 2896, 2895, 2896, 2895, 2896, 2895, 2896, 0, 0, 0, 0, 2914, 2915, 2914, 2915, 2914, 2915, 2914, 2915, 2914, 2915, 2914, 2915, 2914, 2915, 2914, 2915, 2914, 2915, 2914, 2915, 0, 0, 0, 0, 0, 0, 0, 0, 0, 0, 0, 0, 0, 0, 0, 0, 0, 0, 0, 0, 0, 0, 0, 0, 0, 0, 0, 0, 0, 0, 0, 0, 0, 0, 0, 0, 0, 0, 0, 0, 0, 0, 0, 0, 0, 0, 0, 0, 0, 0, 0, 0, 0, 0, 0, 0, 0, 0, 0, 0, 0, 0, 0, 0, 0, 0, 0, 0, 0, 0, 0, 0, 0, 0, 0, 0, 0, 0, 0, 0, 0, 0, 0, 0, 0, 0, 0, 0, 0, 0, 0, 0, 0, 0, 0, 0, 0, 0, 0, 0, 0, 0, 0, 0, 0, 0, 0, 0, 0, 0, 0, 0, 0, 0, 0, 0, 0, 0, 0, 0, 0, 0, 0, 0, 0, 0, 0, 0, 0, 0, 0, 0, 0, 0, 0, 0, 0, 0, 0, 0, 0, 0, 0, 0, 0, 0, 0, 0, 0, 0, 0, 0, 0, 0, 0, 0, 0, 0, 0, 0, 0, 0, 0, 0, 0, 0, 0, 0, 0, 0, 0, 0, 0, 0, 0, 0, 0, 0, 0, 0, 0, 0, 0, 0, 0, 0, 0, 0, 0, 0, 0, 0, 0, 0, 0, 0, 2895, 2896, 2895, 2896, 2895, 2896, 2895, 2896, 2895, 2896, 2895, 2896, 2895, 2896, 2895, 2896, 2895, 2896, 2895, 2896, 0, 0, 0, 0, 2914, 2915, 2914, 2915, 2914, 2915, 2914, 2915, 2914, 2915, 2914, 2915, 2914, 2915, 2914, 2915, 2914, 2915, 2914, 2915, 0, 0, 0, 0, 0, 0, 0, 0, 0, 0, 0, 0, 0, 0, 0, 0, 0, 0, 0, 0, 0, 0, 0, 0, 0, 0, 0, 0, 0, 0, 0, 0, 0, 0, 0, 0, 0, 0, 0, 0, 0, 0, 0, 0, 0, 0, 0, 0, 0, 0, 0, 0, 0, 0, 0, 0, 0, 0, 0, 0, 0, 0, 0, 0, 0, 0, 0, 0, 0, 0, 0, 0, 0, 0, 0, 0, 0, 0, 0, 0, 0, 0, 0, 0, 0, 0, 0, 0, 0, 0, 0, 0, 0, 0, 0, 0, 0, 0, 0, 0, 0, 0, 0, 0, 0, 0, 0, 0, 0, 0, 0, 0, 0, 0, 0, 0, 0, 0, 0, 0, 0, 0],
         "height":31,
         "id":37,
         "name":"deco-10",
         "opacity":1,
         "type":"tilelayer",
         "visible":true,
         "width":24,
         "x":0,
         "y":0
        }, 
        {
         "data":[0, 0, 0, 0, 0, 0, 0, 0, 0, 0, 0, 0, 0, 0, 0, 0, 0, 0, 0, 0, 0, 0, 0, 0, 0, 0, 0, 0, 0, 0, 0, 0, 0, 0, 0, 0, 0, 0, 0, 0, 0, 0, 0, 0, 0, 0, 0, 0, 0, 0, 0, 0, 0, 0, 0, 0, 0, 0, 0, 0, 0, 0, 0, 0, 0, 0, 0, 0, 0, 0, 0, 0, 0, 0, 0, 0, 0, 0, 0, 0, 0, 0, 0, 0, 0, 0, 0, 0, 0, 0, 0, 0, 0, 0, 0, 0, 0, 0, 0, 0, 0, 0, 0, 0, 0, 0, 0, 0, 0, 0, 0, 0, 0, 0, 0, 0, 0, 0, 0, 0, 0, 0, 0, 0, 0, 0, 0, 0, 0, 0, 0, 0, 0, 0, 0, 0, 0, 0, 0, 0, 0, 0, 0, 0, 0, 0, 0, 0, 0, 0, 0, 0, 0, 0, 0, 0, 0, 0, 0, 0, 0, 0, 0, 0, 0, 0, 0, 0, 0, 0, 0, 0, 0, 0, 0, 0, 0, 0, 0, 0, 0, 0, 0, 0, 0, 0, 0, 0, 0, 0, 0, 0, 0, 0, 0, 0, 0, 0, 0, 0, 0, 0, 0, 0, 0, 0, 0, 0, 0, 0, 0, 0, 0, 0, 0, 0, 0, 0, 0, 0, 0, 0, 0, 0, 0, 0, 0, 0, 0, 0, 0, 0, 0, 0, 0, 0, 0, 0, 0, 0, 0, 0, 0, 0, 0, 0, 0, 0, 0, 0, 0, 0, 0, 0, 0, 0, 0, 0, 0, 0, 0, 0, 0, 0, 0, 0, 0, 0, 0, 0, 0, 0, 0, 0, 0, 0, 0, 0, 0, 0, 0, 0, 0, 0, 0, 0, 0, 0, 0, 0, 0, 0, 0, 0, 0, 0, 0, 0, 0, 0, 0, 0, 0, 0, 0, 0, 0, 0, 0, 0, 0, 0, 0, 0, 0, 0, 0, 0, 0, 0, 0, 0, 0, 0, 0, 0, 0, 0, 0, 0, 0, 0, 0, 0, 0, 0, 0, 0, 0, 0, 0, 0, 0, 0, 0, 0, 0, 0, 0, 0, 0, 0, 0, 0, 0, 0, 0, 0, 0, 0, 0, 0, 13746, 13747, 13746, 13747, 13746, 13747, 13746, 13747, 13746, 13747, 13746, 13747, 13746, 13747, 13746, 13747, 13746, 13747, 13746, 13747, 0, 0, 0, 0, 13765, 13766, 13765, 13766, 13765, 13766, 13765, 13766, 13765, 13766, 13765, 13766, 13765, 13766, 13765, 13766, 13765, 13766, 13765, 13766, 0, 0, 0, 0, 0, 0, 0, 0, 0, 0, 0, 0, 0, 0, 0, 0, 0, 0, 0, 0, 0, 0, 0, 0, 0, 0, 0, 0, 0, 0, 0, 0, 0, 0, 0, 0, 0, 0, 0, 0, 0, 0, 0, 0, 0, 0, 0, 0, 0, 0, 0, 0, 0, 0, 0, 0, 0, 0, 0, 0, 0, 0, 0, 0, 0, 0, 0, 0, 0, 0, 0, 0, 0, 0, 0, 0, 0, 0, 0, 0, 0, 0, 0, 0, 0, 0, 0, 0, 0, 0, 0, 0, 0, 0, 0, 0, 0, 0, 0, 0, 0, 0, 0, 0, 0, 0, 0, 0, 0, 0, 0, 0, 0, 0, 0, 0, 0, 0, 0, 0, 0, 0, 0, 0, 0, 0, 0, 0, 0, 0, 0, 0, 0, 0, 0, 0, 0, 0, 0, 0, 0, 0, 0, 0, 0, 0, 0, 0, 0, 0, 0, 0, 0, 0, 0, 0, 0, 0, 0, 0, 0, 0, 0, 0, 0, 0, 0, 0, 0, 0, 0, 0, 0, 0, 0, 0, 0, 0, 0, 0, 0, 0, 0, 0, 0, 0, 0, 0, 0, 0, 0, 0, 0, 0, 0, 0, 13746, 13747, 13746, 13747, 13746, 13747, 13746, 13747, 13746, 13747, 13746, 13747, 13746, 13747, 13746, 13747, 13746, 13747, 13746, 13747, 0, 0, 0, 0, 13765, 13766, 13765, 13766, 13765, 13766, 13765, 13766, 13765, 13766, 13765, 13766, 13765, 13766, 13765, 13766, 13765, 13766, 13765, 13766, 0, 0, 0, 0, 0, 0, 0, 0, 0, 0, 0, 0, 0, 0, 0, 0, 0, 0, 0, 0, 0, 0, 0, 0, 0, 0, 0, 0, 0, 0, 0, 0, 0, 0, 0, 0, 0, 0, 0, 0, 0, 0, 0, 0, 0, 0, 0, 0, 0, 0, 0, 0, 0, 0, 0, 0, 0, 0, 0, 0, 0, 0, 0, 0, 0, 0, 0, 0, 0, 0, 0, 0, 0, 0, 0, 0, 0, 0, 0, 0, 0, 0, 0, 0, 0, 0, 0, 0, 0, 0, 0, 0, 0, 0, 0, 0, 0, 0],
         "height":31,
         "id":38,
         "name":"deco-11",
         "opacity":1,
         "type":"tilelayer",
         "visible":true,
         "width":24,
         "x":0,
         "y":0
        }, 
        {
         "data":[0, 0, 0, 0, 0, 0, 0, 0, 0, 0, 0, 0, 0, 0, 0, 0, 0, 0, 0, 0, 0, 0, 0, 0, 0, 0, 0, 0, 0, 0, 0, 0, 0, 0, 0, 0, 0, 0, 0, 0, 0, 0, 0, 0, 0, 0, 0, 0, 0, 0, 0, 0, 0, 0, 0, 0, 0, 0, 0, 0, 0, 0, 0, 0, 0, 0, 0, 0, 0, 0, 0, 0, 0, 0, 0, 0, 0, 0, 0, 0, 0, 0, 0, 0, 0, 0, 0, 0, 0, 0, 0, 0, 0, 0, 0, 0, 0, 0, 0, 0, 0, 0, 0, 0, 0, 0, 0, 0, 0, 0, 0, 0, 0, 0, 0, 0, 0, 0, 0, 0, 0, 0, 0, 0, 0, 0, 0, 0, 0, 0, 0, 0, 0, 0, 0, 0, 0, 0, 0, 0, 0, 0, 0, 0, 0, 0, 0, 0, 0, 0, 0, 0, 0, 0, 0, 0, 0, 0, 0, 0, 0, 0, 0, 0, 0, 0, 0, 0, 0, 0, 0, 0, 0, 0, 0, 0, 0, 0, 0, 0, 0, 0, 0, 0, 0, 0, 0, 0, 0, 0, 0, 0, 0, 0, 0, 0, 0, 0, 0, 0, 0, 0, 0, 0, 0, 0, 0, 0, 0, 0, 0, 0, 0, 0, 0, 0, 0, 0, 0, 0, 0, 0, 0, 0, 0, 0, 0, 0, 0, 0, 0, 0, 0, 0, 0, 0, 0, 0, 0, 0, 0, 0, 0, 0, 0, 0, 0, 0, 0, 0, 0, 0, 0, 0, 0, 0, 0, 0, 0, 0, 0, 0, 0, 0, 0, 0, 0, 0, 0, 0, 0, 0, 0, 0, 0, 0, 0, 0, 0, 0, 0, 0, 0, 0, 0, 0, 0, 0, 0, 0, 0, 0, 0, 0, 0, 0, 0, 0, 0, 0, 0, 0, 0, 0, 0, 0, 0, 0, 0, 0, 0, 0, 0, 0, 0, 0, 0, 0, 0, 0, 0, 0, 0, 0, 0, 0, 0, 0, 0, 0, 0, 0, 0, 0, 0, 0, 0, 0, 0, 0, 0, 0, 0, 0, 0, 0, 0, 0, 0, 0, 0, 0, 0, 0, 0, 0, 0, 0, 0, 0, 0, 0, 0, 0, 0, 0, 0, 0, 0, 0, 0, 0, 0, 0, 0, 0, 0, 0, 0, 0, 0, 0, 0, 0, 0, 0, 2895, 2896, 2895, 2896, 2895, 2896, 2895, 2896, 2895, 2896, 2895, 2896, 2895, 2896, 2895, 2896, 2895, 2896, 2895, 2896, 0, 0, 0, 0, 0, 0, 0, 0, 0, 0, 0, 0, 0, 0, 0, 0, 0, 0, 0, 0, 0, 0, 0, 0, 0, 0, 0, 0, 0, 0, 0, 0, 0, 0, 0, 0, 0, 0, 0, 0, 0, 0, 0, 0, 0, 0, 0, 0, 0, 0, 0, 0, 0, 0, 0, 0, 0, 0, 0, 0, 0, 0, 0, 0, 0, 0, 0, 0, 0, 0, 0, 0, 0, 0, 0, 0, 0, 0, 0, 0, 0, 0, 0, 0, 0, 0, 0, 0, 0, 0, 0, 0, 0, 0, 0, 0, 0, 0, 0, 0, 0, 0, 0, 0, 0, 0, 0, 0, 0, 0, 0, 0, 0, 0, 0, 0, 0, 0, 0, 0, 0, 0, 0, 0, 0, 0, 0, 0, 0, 0, 0, 0, 0, 0, 0, 0, 0, 0, 0, 0, 0, 0, 0, 0, 0, 0, 0, 0, 0, 0, 0, 0, 0, 0, 0, 0, 0, 0, 0, 0, 0, 0, 0, 0, 0, 0, 0, 0, 0, 0, 0, 0, 0, 0, 0, 0, 0, 0, 0, 0, 0, 0, 0, 0, 0, 0, 0, 0, 0, 0, 0, 0, 0, 0, 0, 0, 0, 0, 0, 0, 0, 0, 0, 0, 0, 0, 0, 0, 0, 0, 0, 0, 0, 0, 0, 0, 0, 0, 0, 0, 2895, 2896, 2895, 2896, 2895, 2896, 2895, 2896, 2895, 2896, 2895, 2896, 2895, 2896, 2895, 2896, 2895, 2896, 2895, 2896, 0, 0, 0, 0, 2914, 2915, 2914, 2915, 2914, 2915, 2914, 2915, 2914, 2915, 2914, 2915, 2914, 2915, 2914, 2915, 2914, 2915, 2914, 2915, 0, 0, 0, 0, 0, 0, 0, 0, 0, 0, 0, 0, 0, 0, 0, 0, 0, 0, 0, 0, 0, 0, 0, 0, 0, 0, 0, 0, 0, 0, 0, 0, 0, 0, 0, 0, 0, 0, 0, 0, 0, 0, 0, 0, 0, 0, 0, 0, 0, 0, 0, 0, 0, 0, 0, 0, 0, 0, 0, 0, 0, 0, 0, 0, 0, 0, 0, 0, 0, 0, 0, 0, 0, 0],
         "height":31,
         "id":39,
         "name":"deco-12",
         "opacity":1,
         "type":"tilelayer",
         "visible":true,
         "width":24,
         "x":0,
         "y":0
        }, 
        {
         "draworder":"topdown",
         "id":3,
         "name":"floorLayer",
         "objects":[],
         "opacity":1,
         "type":"objectgroup",
         "visible":true,
         "x":0,
         "y":0
        }, 
        {
         "data":[0, 0, 0, 0, 0, 0, 0, 0, 0, 0, 0, 0, 0, 0, 0, 0, 0, 0, 0, 0, 0, 0, 0, 0, 0, 0, 0, 0, 0, 0, 0, 0, 0, 0, 0, 0, 0, 0, 0, 0, 0, 0, 0, 0, 0, 0, 0, 0, 0, 0, 0, 0, 0, 0, 0, 0, 0, 0, 0, 0, 0, 0, 0, 0, 0, 0, 0, 0, 0, 0, 0, 0, 0, 0, 0, 0, 0, 0, 0, 0, 0, 0, 0, 0, 0, 0, 0, 0, 0, 0, 0, 0, 0, 0, 0, 0, 0, 0, 0, 0, 0, 0, 0, 0, 0, 0, 0, 0, 0, 0, 0, 0, 0, 0, 0, 0, 0, 0, 0, 0, 0, 0, 0, 0, 0, 0, 0, 0, 0, 0, 0, 0, 0, 0, 0, 0, 0, 0, 0, 0, 0, 0, 0, 0, 0, 0, 0, 0, 0, 0, 0, 0, 0, 0, 0, 0, 0, 0, 0, 0, 0, 0, 0, 0, 0, 0, 0, 0, 0, 0, 0, 0, 0, 0, 0, 0, 0, 0, 0, 0, 0, 0, 0, 0, 0, 0, 0, 0, 0, 0, 0, 0, 0, 0, 0, 0, 0, 0, 0, 0, 0, 0, 0, 0, 0, 0, 0, 0, 0, 0, 0, 0, 0, 0, 0, 0, 0, 0, 0, 0, 0, 0, 0, 0, 0, 0, 0, 0, 0, 0, 0, 0, 0, 0, 0, 0, 0, 0, 0, 0, 0, 0, 0, 0, 0, 0, 0, 0, 0, 0, 0, 0, 0, 0, 0, 0, 0, 0, 0, 0, 0, 0, 0, 0, 0, 0, 0, 0, 0, 0, 0, 0, 0, 0, 0, 0, 0, 0, 0, 0, 0, 0, 0, 0, 0, 0, 0, 0, 0, 0, 0, 0, 0, 0, 0, 0, 0, 0, 0, 0, 0, 0, 0, 0, 0, 0, 0, 0, 0, 0, 0, 0, 0, 0, 0, 0, 0, 0, 0, 0, 0, 0, 0, 0, 0, 0, 0, 0, 0, 0, 0, 0, 0, 0, 0, 0, 0, 0, 0, 0, 0, 0, 0, 0, 0, 0, 0, 0, 0, 0, 0, 0, 0, 0, 0, 0, 0, 0, 0, 0, 0, 0, 0, 0, 0, 0, 0, 0, 0, 0, 0, 0, 0, 0, 0, 0, 0, 0, 0, 0, 0, 0, 0, 0, 0, 0, 0, 0, 0, 0, 0, 0, 0, 0, 0, 0, 0, 0, 0, 0, 0, 0, 0, 0, 0, 0, 0, 0, 0, 0, 0, 0, 0, 0, 0, 0, 0, 0, 0, 0, 0, 0, 0, 0, 0, 0, 0, 0, 0, 0, 0, 0, 0, 0, 0, 0, 0, 0, 0, 0, 0, 0, 0, 0, 0, 0, 0, 0, 0, 0, 0, 0, 0, 0, 0, 0, 0, 0, 0, 0, 0, 0, 0, 0, 0, 0, 0, 0, 0, 0, 0, 0, 0, 0, 0, 0, 0, 0, 0, 0, 0, 0, 0, 0, 0, 0, 0, 0, 0, 0, 0, 0, 0, 0, 0, 0, 0, 0, 0, 0, 0, 0, 0, 0, 0, 0, 0, 0, 0, 0, 0, 0, 0, 0, 0, 0, 0, 0, 0, 0, 0, 0, 0, 0, 0, 0, 0, 0, 0, 0, 0, 0, 0, 0, 0, 0, 0, 0, 0, 0, 0, 0, 0, 0, 0, 0, 0, 0, 0, 0, 0, 0, 0, 0, 0, 0, 0, 0, 0, 0, 0, 0, 0, 0, 0, 0, 0, 0, 0, 0, 0, 0, 0, 0, 0, 0, 0, 0, 0, 0, 0, 0, 0, 0, 0, 0, 0, 0, 0, 0, 0, 0, 0, 0, 0, 0, 0, 0, 0, 0, 0, 0, 0, 0, 0, 0, 0, 0, 0, 0, 0, 0, 0, 0, 0, 0, 0, 0, 0, 0, 0, 0, 0, 0, 0, 0, 0, 0, 0, 0, 0, 0, 0, 0, 0, 0, 0, 0, 0, 0, 0, 0, 0, 0, 0, 0, 0, 0, 0, 0, 0, 0, 0, 0, 0, 0, 0, 0, 0, 0, 0, 0, 0, 0, 0, 0, 0, 0, 0, 0, 0, 0, 0, 0, 0, 0, 0, 0, 0, 0, 0, 0, 0, 0, 0, 0, 0, 0, 0, 0, 0, 0, 0, 0, 0, 0, 0, 0, 0, 0, 0, 0, 0, 0, 0, 0, 0, 0, 0, 0, 0, 0, 0, 0, 0, 0, 0, 0, 0, 0, 0, 0, 0, 0, 0, 0, 0, 0, 0, 0, 0, 0, 0, 0, 0, 0, 0, 0, 0, 0, 0, 0, 0, 0],
         "height":31,
         "id":7,
         "name":"amenagement",
         "opacity":1,
         "properties":[
                {
                 "name":"depth",
                 "type":"int",
                 "value":3
                }],
         "type":"tilelayer",
         "visible":true,
         "width":24,
         "x":0,
         "y":0
        }, 
        {
         "data":[0, 0, 0, 0, 0, 0, 0, 0, 0, 0, 0, 0, 0, 0, 0, 0, 0, 0, 0, 0, 0, 0, 0, 0, 0, 0, 0, 0, 0, 0, 0, 0, 0, 0, 0, 0, 0, 0, 0, 0, 0, 0, 0, 0, 0, 0, 0, 0, 0, 0, 0, 0, 0, 0, 0, 0, 0, 0, 0, 0, 0, 0, 0, 0, 0, 0, 0, 0, 0, 0, 0, 0, 0, 0, 0, 0, 0, 0, 0, 0, 0, 0, 0, 0, 0, 0, 0, 0, 0, 0, 0, 0, 0, 0, 0, 0, 0, 0, 0, 0, 0, 0, 0, 0, 0, 0, 0, 0, 0, 0, 0, 0, 0, 0, 0, 0, 0, 0, 0, 0, 0, 0, 0, 0, 0, 0, 0, 0, 0, 0, 0, 0, 0, 0, 0, 0, 0, 0, 0, 0, 0, 0, 0, 0, 0, 0, 0, 0, 0, 0, 0, 0, 0, 0, 0, 0, 0, 0, 0, 0, 0, 0, 0, 0, 0, 0, 0, 0, 0, 0, 0, 0, 0, 0, 0, 0, 0, 0, 0, 0, 0, 0, 0, 0, 0, 0, 0, 0, 0, 0, 0, 0, 0, 0, 0, 0, 0, 0, 0, 0, 0, 0, 0, 0, 0, 0, 0, 0, 0, 0, 0, 0, 0, 0, 0, 0, 0, 0, 0, 0, 0, 0, 0, 0, 0, 0, 0, 0, 0, 0, 0, 0, 0, 0, 0, 0, 0, 0, 0, 0, 0, 0, 0, 0, 0, 0, 0, 0, 0, 0, 0, 0, 0, 0, 0, 0, 0, 0, 0, 0, 0, 0, 0, 0, 0, 0, 0, 0, 0, 0, 0, 0, 0, 0, 0, 0, 0, 0, 0, 0, 0, 0, 0, 0, 0, 0, 0, 0, 0, 0, 0, 0, 0, 0, 0, 0, 0, 0, 0, 0, 0, 0, 0, 0, 0, 0, 0, 0, 0, 0, 0, 0, 0, 0, 0, 0, 0, 0, 0, 0, 0, 0, 0, 0, 0, 0, 0, 0, 0, 0, 0, 0, 0, 0, 0, 0, 0, 0, 0, 0, 0, 0, 0, 0, 0, 0, 0, 0, 0, 0, 0, 0, 0, 0, 0, 0, 0, 0, 0, 0, 0, 0, 0, 0, 0, 0, 0, 0, 0, 0, 0, 0, 0, 0, 0, 0, 0, 0, 0, 0, 0, 0, 0, 0, 0, 0, 0, 0, 0, 0, 0, 0, 0, 0, 0, 0, 0, 0, 0, 0, 0, 0, 0, 0, 0, 0, 0, 0, 0, 0, 0, 0, 0, 0, 0, 0, 0, 0, 0, 0, 0, 0, 0, 0, 0, 0, 0, 0, 0, 0, 0, 0, 0, 0, 0, 0, 0, 0, 0, 0, 0, 0, 0, 0, 0, 0, 0, 0, 0, 0, 0, 0, 0, 0, 0, 0, 0, 0, 0, 0, 0, 0, 0, 0, 0, 0, 0, 0, 0, 0, 0, 0, 0, 0, 0, 0, 0, 0, 0, 0, 0, 0, 0, 0, 0, 0, 0, 0, 0, 0, 0, 0, 0, 0, 0, 0, 0, 0, 0, 0, 0, 0, 0, 0, 0, 0, 0, 0, 0, 0, 0, 0, 0, 0, 0, 0, 0, 0, 0, 0, 0, 0, 0, 0, 0, 0, 0, 0, 0, 0, 0, 0, 0, 0, 0, 0, 0, 0, 0, 0, 0, 0, 0, 0, 0, 0, 0, 0, 0, 0, 0, 0, 0, 0, 0, 0, 0, 0, 0, 0, 0, 0, 0, 0, 0, 0, 0, 0, 0, 0, 0, 0, 0, 0, 0, 0, 0, 0, 0, 0, 0, 0, 0, 0, 0, 0, 0, 0, 0, 0, 0, 0, 0, 0, 0, 0, 0, 0, 0, 0, 0, 0, 0, 0, 0, 0, 0, 0, 0, 0, 0, 0, 0, 0, 0, 0, 0, 0, 0, 0, 0, 0, 0, 0, 0, 0, 0, 0, 0, 0, 0, 0, 0, 0, 0, 0, 0, 0, 0, 0, 0, 0, 0, 0, 0, 0, 0, 0, 0, 0, 0, 0, 0, 0, 0, 0, 0, 0, 0, 0, 0, 0, 0, 0, 0, 0, 0, 0, 0, 0, 0, 0, 0, 0, 0, 0, 0, 0, 0, 0, 0, 0, 0, 0, 0, 0, 0, 0, 0, 0, 0, 0, 0, 0, 0, 0, 0, 0, 0, 0, 0, 0, 0, 0, 0, 0, 0, 0, 0, 0, 0, 0, 0, 0, 0, 0, 0, 0, 0, 0, 0, 0, 0, 0, 0, 0, 0, 0, 0, 0, 0, 0, 0, 0, 0, 0, 0, 0, 0, 0, 0, 0, 0, 0],
         "height":31,
         "id":14,
         "name":"ordi",
         "opacity":1,
         "properties":[
                {
                 "name":"depth",
                 "type":"int",
                 "value":3
                }],
         "type":"tilelayer",
         "visible":true,
         "width":24,
         "x":0,
         "y":0
        }],
 "nextlayerid":47,
 "nextobjectid":1,
 "orientation":"orthogonal",
 "properties":[
        {
         "name":"mapCopyright",
         "type":"string",
         "value":"CC-BY-SA 3.0:\n - http:\/\/creativecommons.org\/licenses\/by-sa\/3.0\/\n - See the file: cc-by-sa-3.0.txt\nGNU GPL 3.0:\n - http:\/\/www.gnu.org\/licenses\/gpl-3.0.html\n - See the file: gpl-3.0.txt\n\nAssets from: workadventure@thecodingmachine.com"
        }, 
        {
         "name":"mapDescription",
         "type":"string",
         "value":"Custom map NordAgile"
        }, 
        {
         "name":"mapImage",
         "type":"string",
         "value":"amphi.png"
        }, 
        {
         "name":"mapLink",
         "type":"string",
         "value":""
        }, 
        {
         "name":"mapName",
         "type":"string",
         "value":"Amphi"
        }],
 "renderorder":"right-down",
 "tiledversion":"1.5.0",
 "tileheight":32,
 "tilesets":[
        {
         "columns":19,
         "firstgid":1,
         "image":"modern_interiors_2.png",
         "imageheight":7040,
         "imagewidth":608,
         "margin":0,
         "name":"modern_interiors_2",
         "spacing":0,
         "tilecount":4180,
         "tileheight":32,
         "tilewidth":32
        }, 
        {
         "columns":40,
         "firstgid":4181,
         "image":"modern_tileset.png",
         "imageheight":1856,
         "imagewidth":1280,
         "margin":0,
         "name":"modern_tileset",
         "spacing":0,
         "tilecount":2320,
         "tileheight":32,
         "tilewidth":32
        }, 
        {
         "columns":19,
         "firstgid":6501,
         "image":"modern_interiors_1.png",
         "imageheight":7328,
         "imagewidth":608,
         "margin":0,
         "name":"modern_interiors_1",
         "spacing":0,
         "tilecount":4351,
         "tileheight":32,
         "tilewidth":32
        }, 
        {
         "columns":19,
         "firstgid":10852,
         "image":"modern_interiors_nightmode_2.png",
         "imageheight":5760,
         "imagewidth":608,
         "margin":0,
         "name":"modern_interiors_nightmode_2",
         "spacing":0,
         "tilecount":3420,
         "tileheight":32,
         "tilewidth":32
        }, 
        {
         "columns":19,
         "firstgid":14272,
         "image":"modern_interiors_nightmode_1.png",
         "imageheight":7328,
         "imagewidth":608,
         "margin":0,
         "name":"modern_interiors_nightmode_1",
         "spacing":0,
         "tilecount":4351,
         "tileheight":32,
         "tilewidth":32
        }, 
        {
         "columns":32,
         "firstgid":18623,
         "image":"Exterior Tiles.png",
         "imageheight":1024,
         "imagewidth":1024,
         "margin":0,
         "name":"Exterior Tiles",
         "spacing":0,
         "tilecount":1024,
         "tileheight":32,
         "tilewidth":32
        }, 
        {
         "columns":13,
         "firstgid":19647,
         "image":"work_adventure_tilesets_ag.png",
         "imageheight":1184,
         "imagewidth":416,
         "margin":0,
         "name":"work_adventure_tilesets_ag",
         "spacing":0,
         "tilecount":481,
         "tileheight":32,
         "tilewidth":32
        }, 
        {
         "columns":32,
         "firstgid":20128,
         "image":"LPC-interiors-1-submissions.png",
         "imageheight":1024,
         "imagewidth":1024,
         "margin":0,
         "name":"LPC-interiors-1-submissions",
         "spacing":0,
         "tilecount":1024,
         "tileheight":32,
         "tilewidth":32
        }, 
        {
         "columns":5,
         "firstgid":21152,
         "image":"watileset.png",
         "imageheight":512,
         "imagewidth":160,
         "margin":0,
         "name":"watileset",
         "spacing":0,
         "tilecount":80,
         "tileheight":32,
         "tiles":[
                {
                 "id":0,
                 "properties":[
                        {
                         "name":"collides",
                         "type":"bool",
                         "value":true
                        }]
                }],
         "tilewidth":32
        }],
 "tilewidth":32,
 "type":"map",
 "version":1.5,
 "width":24
}